Workbook

Sheet Cover
B2: INVIRTUS
B3: Bottoms-Up Revenue Potential (two streams; TAM / SAM / SOM equivalents)
B4: Candidate assessment platform - decision intelligence layer above the ATS | USD | Built 2026-06-16
B6: THE ANSWER
B7: Lead with the 3-year reachable number. It runs on two streams - assessment packs plus talent-DB monetization - and is driven first by the Manatal channel (embedded attach ~59% of the assessment line), then self-serve. The single biggest assumption is the Year-3 channel attach rate on the ICP-relevant Manatal base (Assumptions sec. 7); tests/account and the $14 PAYG price are the next two swing factors (see Sensitivity).
B11: FULL OPPORTUNITY | C11: SERVICEABLE TODAY | D11: 3-YEAR REACHABLE
B12: =Build!$F$37 | C12: =Build!$F$38 | D12: =Build!$F$39
B13: (TAM) all geos | 2 streams | C13: (SAM) focus-6 | serviceable | D13: (SOM) channel+direct | 3-yr
B15: 3-yr reachable - by revenue stream
B16: Assessment packs | C16: =Build!$C$39
B17: Talent-DB monetization | C17: =Build!$E$39
B18: Total revenue potential | C18: =Build!$F$39
B20: 3-yr reachable - assessments by route
B21: Channel (partner portfolio) | C21: =Build!$E$24
B22: Direct (self-serve + sales) | C22: =Build!$E$30
B24: Scenario levers (edit on Assumptions)
B25: Market breadth mode | C25: =Assumptions!$C$33
B26: Channel attach scalar | C26: =Assumptions!$C$90
B28: How to read this model
B29: 1. Every blue cell on Assumptions is an editable input; black cells are formulas with no hardcodes.
B30: 2. Market BREADTH toggle (1 Engineers / 2 White-collar / 3 Narrower) scales the universe; the
B31: headline above reflects the active mode. Channel is a partner PORTFOLIO (Manatal + others), each toggleable.
B32: 3. Build derives Serviceable bottoms-up (entities x %fit x tests/yr x net $/test), grosses up to Full
B33: opportunity, and captures the 3-yr figure via the partner channel + direct self-serve/sales, two streams.
B34: 4. Sensitivity flexes the inputs that move it most; Sources lists every researched figure.
B36: Input (editable) | C36: Formula (calc)

Sheet Assumptions
B1: INVIRTUS - Assumptions
B2: All blue cells are editable inputs. Black cells are formulas. Col E = source key (see Sources tab). Currency = USD.
B4: Driver | C4: Value | D4: Unit | E4: Src | F4: Logic / flag
B5: 1. Addressable entities (bottoms-up universe) [RESEARCH]
B6: Tech-focused recruiting agencies
B7: France | C7: 500 | D7: entities | E7: S1 | F7: Recruitment/staffing firms with a tech/IT desk. Tech subset of national agency base.
B8: UK | C8: 3500 | D8: entities | E8: S2 | F8: Recruitment/staffing firms with a tech/IT desk. Tech subset of national agency base.
B9: UAE | C9: 100 | D9: entities | E9: S3 | F9: Recruitment/staffing firms with a tech/IT desk. Tech subset of national agency base.
B10: Morocco | C10: 45 | D10: entities | E10: S4 | F10: Recruitment/staffing firms with a tech/IT desk. Tech subset of national agency base.
B11: KSA | C11: 50 | D11: entities | E11: S5 | F11: Recruitment/staffing firms with a tech/IT desk. Tech subset of national agency base.
B12: Egypt | C12: 60 | D12: entities | E12: S6 | F12: Recruitment/staffing firms with a tech/IT desk. Tech subset of national agency base.
B13: Engineering-heavy firms (tech/software/ICT cos.)
B14: France | C14: 95000 | D14: entities | E14: S1 | F14: Tech/software/ICT companies that hire engineers in-house.
B15: UK | C15: 107000 | D15: entities | E15: S2 | F15: Tech/software/ICT companies that hire engineers in-house.
B16: UAE | C16: 5000 | D16: entities | E16: S3 | F16: Tech/software/ICT companies that hire engineers in-house.
B17: Morocco | C17: 2000 | D17: entities | E17: S4 | F17: Tech/software/ICT companies that hire engineers in-house.
B18: KSA | C18: 1800 | D18: entities | E18: S5 | F18: Tech/software/ICT companies that hire engineers in-house.
B19: Egypt | C19: 2500 | D19: entities | E19: S6 | F19: Tech/software/ICT companies that hire engineers in-house.
B20: Mid-size firms w/ structured tech hiring (50-250)
B21: France | C21: 7300 | D21: entities | E21: S1 | F21: Medium enterprises x share that run structured engineering hiring.
B22: UK | C22: 13200 | D22: entities | E22: S2 | F22: Medium enterprises x share that run structured engineering hiring.
B23: UAE | C23: 2800 | D23: entities | E23: S3 | F23: Medium enterprises x share that run structured engineering hiring.
B24: Morocco | C24: 1250 | D24: entities | E24: S4 | F24: Medium enterprises x share that run structured engineering hiring.
B25: KSA | C25: 2600 | D25: entities | E25: S5 | F25: Medium enterprises x share that run structured engineering hiring.
B26: Egypt | C26: 2000 | D26: entities | E26: S6 | F26: Medium enterprises x share that run structured engineering hiring.
B27: Focus-6 subtotals (calc)
B28: Agencies - focus-6 total | C28: =(Assumptions!$C$7+Assumptions!$C$8+Assumptions!$C$9+Assumptions!$C$10+Assumptions!$C$11+Assumptions!$C$12) | D28: entities | F28: Sum across France, UK, UAE, Morocco, KSA, Egypt.
B29: Eng-heavy firms - focus-6 total | C29: =(Assumptions!$C$14+Assumptions!$C$15+Assumptions!$C$16+Assumptions!$C$17+Assumptions!$C$18+Assumptions!$C$19) | D29: entities | F29: Sum across France, UK, UAE, Morocco, KSA, Egypt.
B30: Mid-size firms - focus-6 total | C30: =(Assumptions!$C$21+Assumptions!$C$22+Assumptions!$C$23+Assumptions!$C$24+Assumptions!$C$25+Assumptions!$C$26) | D30: entities | F30: Sum across France, UK, UAE, Morocco, KSA, Egypt.
B31: 1b. Market breadth toggle (1=Engineers, 2=White-collar, 3=Narrower)
B32: Active breadth mode (1 / 2 / 3) | C32: 1 | D32: mode | F32: 1: tech/eng focus (current). 2: all structured white-collar hiring (Aida's broader view). 3: narrower high-conviction core.
B33: Active breadth (label) | C33: =CHOOSE(Assumptions!$C$32,"1 Engineers only","2 White-collar hiring","3 Narrower use case") | F33: Driven by the toggle above.
B34: Breadth multiplier by segment | C34: 1 Eng | D34: 2 White-collar | E34: 3 Narrower | F34: Logic
B35: Agencies | C35: 1 | D35: 7 | E35: 1 | F35: Tech agencies -> all recruitment agencies (tech ~10-15% of total).
B36: Eng-heavy firms | C36: 1 | D36: 4 | E36: 0.5 | F36: Tech firms -> all firms with structured white-collar hiring.
B37: Mid-size firms | C37: 1 | D37: 3 | E37: 0.2 | F37: Eng-hiring mid-size -> all mid-size structured hirers (2) / core only (3).
B38: Effective addressable entities (calc = subtotal x active breadth mult)
B39: Agencies - effective | C39: =Assumptions!$C$28*CHOOSE(Assumptions!$C$32,$C$35,$D$35,$E$35) | D39: entities | F39: Focus-6 subtotal x active breadth multiplier.
B40: Eng-heavy firms - effective | C40: =Assumptions!$C$29*CHOOSE(Assumptions!$C$32,$C$36,$D$36,$E$36) | D40: entities | F40: Focus-6 subtotal x active breadth multiplier.
B41: Mid-size firms - effective | C41: =Assumptions!$C$30*CHOOSE(Assumptions!$C$32,$C$37,$D$37,$E$37) | D41: entities | F41: Focus-6 subtotal x active breadth multiplier.
B42: 2. Share that fits the structured-evaluation use case
B43: Agencies - % fit use case | C43: 0.55 | D43: % | F43: Tech recruiting agencies run high req volume; structured assessment is core to their value-add. High fit.
B44: Eng-heavy firms - % fit use case | C44: 0.15 | D44: % | F44: Broad tech-firm base is ~95% micro (<50 staff, solo dev shops). Only volume hirers run structured multi-candidate evaluation. Deliberately low.
B45: Mid-size firms - % fit use case | C45: 0.25 | D45: % | F45: ICP pain (inconsistent evaluation) but lower adoption propensity / hire sporadically. Conservative.
B46: 3. Pricing (usage-based: $/test, packs) [given]
B47: PAYG base price per test | C47: 14 | D47: $/test | E47: S7 | F47: Finalized BP base (was $15). Benchmark: TestGorilla ~$4.3/candidate, TestDome $7-20, HackerRank $15-20, Adaface entry $15. $14 sits at premium end.
B48: Small pack discount (20 tests) | C48: 0.1 | D48: % | F48: Given.
B49: Medium pack discount (100 tests) | C49: 0.15 | D49: % | F49: Given.
B50: Enterprise pack discount (1,000 tests) | C50: 0.2 | D50: % | F50: Finalized BP top tier: 1,000-test Enterprise pack at $11,200 (= $11.20/test). Replaces old 200-unit Large and the flat enterprise fee.
B51: Net price - PAYG | C51: =Assumptions!$C$47 | D51: $/test
B52: Net price - Small | C52: =Assumptions!$C$47*(1-Assumptions!$C$48) | D52: $/test
B53: Net price - Medium | C53: =Assumptions!$C$47*(1-Assumptions!$C$49) | D53: $/test
B54: Net price - Enterprise (1,000-pack) | C54: =Assumptions!$C$47*(1-Assumptions!$C$50) | D54: $/test
B55: 4. Pack mix (share of accounts on each plan) [pack-led per finalized BP]
B56: PAYG share | C56: 0.1 | D56: % | F56: Finalized BP is pack-led; PAYG is a thin trial tier, not the base.
B57: Small pack share | C57: 0.35 | D57: %
B58: Medium pack share | C58: 0.35 | D58: %
B59: Enterprise (1,000-pack) share | C59: 0.2 | D59: % | F59: Heaviest buyers; matches finalized BP customer mix.
B60: Mix check (=100%) | C60: =Assumptions!$C$56+Assumptions!$C$57+Assumptions!$C$58+Assumptions!$C$59 | D60: % | F60: Must equal 100%.
B61: Blended net price per test | C61: =(Assumptions!$C$56*Assumptions!$C$51+Assumptions!$C$57*Assumptions!$C$52+Assumptions!$C$58*Assumptions!$C$53+Assumptions!$C$59*Assumptions!$C$54)/(Assumptions!$C$56+Assumptions!$C$57+Assumptions!$C$58+Assumptions!$C$59) | D61: $/test | F61: Mix-weighted net price across all four packs.
B62: 5. Tests per account / year (roles x candidates per role)
B63: Tests-per-account scalar (sensitivity handle) | C63: 1 | D63: x | F63: Global multiplier on tests/account. Base=1.00; flex in sensitivity.
B64: Agencies - roles hired / yr | C64: 80 | D64: roles | F64: High req throughput - many client roles, several candidates screened each.
B65: Agencies - candidates tested / role | C65: 6 | D65: cand
B66: Agencies - tests / account / yr | C66: =Assumptions!$C$64*Assumptions!$C$65*Assumptions!$C$63 | D66: tests | F66: roles x candidates x scalar.
B67: Eng-heavy firms - roles hired / yr | C67: 25 | D67: roles | F67: Steady in-house eng hiring.
B68: Eng-heavy firms - candidates tested / role | C68: 6 | D68: cand
B69: Eng-heavy firms - tests / account / yr | C69: =Assumptions!$C$67*Assumptions!$C$68*Assumptions!$C$63 | D69: tests | F69: roles x candidates x scalar.
B70: Mid-size firms - roles hired / yr | C70: 10 | D70: roles | F70: Sporadic, lower-volume hiring.
B71: Mid-size firms - candidates tested / role | C71: 5 | D71: cand
B72: Mid-size firms - tests / account / yr | C72: =Assumptions!$C$70*Assumptions!$C$71*Assumptions!$C$63 | D72: tests | F72: roles x candidates x scalar.
B73: Channel acct - roles hired / yr | C73: 40 | D73: roles | F73: Manatal users: mix of agencies + in-house recruiters.
B74: Channel acct - candidates tested / role | C74: 5 | D74: cand
B75: Channel acct - tests / account / yr | C75: =Assumptions!$C$73*Assumptions!$C$74*Assumptions!$C$63 | D75: tests
B76: 6. ACV per account (revenue/yr)
B77: Agencies - ACV / account / yr | C77: =Assumptions!$C$66*Assumptions!$C$61 | D77: $/yr | F77: tests/account x blended net price per test.
B78: Eng-heavy firms - ACV / account / yr | C78: =Assumptions!$C$69*Assumptions!$C$61 | D78: $/yr | F78: tests/account x blended net price per test.
B79: Mid-size firms - ACV / account / yr | C79: =Assumptions!$C$72*Assumptions!$C$61 | D79: $/yr | F79: tests/account x blended net price per test.
B80: Channel acct - ACV / account / yr | C80: =Assumptions!$C$75*Assumptions!$C$61 | D80: $/yr | F80: tests/account x blended net price per test.
B81: 7. SOM - Channel: partner distribution portfolio [beyond Manatal]
B82: Partner (set On=1 to include) | C82: On 1/0 | D82: Client base | E82: ICP-rel% | F82: Attach y3 | G82: Accounts
B83: Manatal (ATS, live) | C83: 1 | D83: 10000 | E83: 0.45 | F83: 0.08 | G83: =C83*D83*E83*F83 | H83: S8
B84: Socium (2nd ATS, exploring) | C84: 1 | D84: 3000 | E84: 0.45 | F84: 0.05 | G84: =C84*D84*E84*F84 | H84: S9
B85: Other HR-tech / ATS players | C85: 1 | D85: 15000 | E85: 0.35 | F85: 0.03 | G85: =C85*D85*E85*F85
B86: Staffing-firm networks | C86: 1 | D86: 5000 | E86: 0.6 | F86: 0.04 | G86: =C86*D86*E86*F86
B87: HR consultancies | C87: 1 | D87: 3000 | E87: 0.5 | F87: 0.04 | G87: =C87*D87*E87*F87
B88: System integrators | C88: 1 | D88: 2000 | E88: 0.4 | F88: 0.03 | G88: =C88*D88*E88*F88
B89: Channel base accounts (portfolio, y3) | G89: =SUM(G83:G88)
B90: Channel attach scalar (sensitivity handle) | C90: 1 | D90: x | F90: Global multiplier on all partner attach rates. Base=1.00; flex in sensitivity. (Channel tests/acct & ACV in secs 5-6.)
B91: 8. SOM - Direct route (self-serve + sales-led)
B92: 3-yr penetration of serviceable SAM accounts | C92: 0.008 | D92: % | F92: Direct capture is gated by low trial-to-paid; a pre-seed wins only a thin slice of the large serviceable base.
B93: Monthly website traffic | C93: 8000 | D93: visits/mo | F93: Self-serve funnel cross-check input (year-3 run-rate).
B94: Visit -> free-trial conversion | C94: 0.03 | D94: %
B95: Trial -> paid conversion | C95: 0.05 | D95: % | E95: S8 | F95: Currently LOW - do NOT assume best-in-class. Flagged in GTM notes.
B96: 9. Retention & global scope
B97: Steady-state annual retention | C97: 0.9 | D97: % | E97: S8 | F97: Finalized BP assumes 7% gross churn (93% retention); held slightly conservative at 90% for the SOM. 100% to date on a tiny base.
B98: Focus-6 share of global addressable universe | C98: 0.12 | D98: % | F98: Focus-6 as % of all geos where product works. Grosses SAM up to TAM. US/India/rest-EU dominate.
B99: 10. Value delivered (cost-of-bad-hire anchor)
B100: Cost of a bad hire | C100: 150000 | D100: $ | E100: S8 | F100: Core value anchor used across sales & fundraising.
B101: Tests run per hire placed | C101: 6 | D101: tests | F101: Candidates assessed per filled role (1 hire/role).
...

Sheet Build
B1: INVIRTUS - Revenue potential build (TAM / SAM / SOM)
B2: Bottoms-up: entities x %fit x tests/yr x net $/test, plus talent-DB stream. USD. All drivers live on Assumptions.
B4: A. Serviceable accounts (focus-6 = SAM geography)
B5: Segment | C5: Entities (focus-6) | D5: % fit | E5: Serviceable accts | F5: Tests/acct/yr | G5: ACV/acct ($) | H5: SAM value ($/yr)
B6: Tech recruiting agencies | C6: =Assumptions!$C$39 | D6: =Assumptions!$C$43 | E6: =C6*D6 | F6: =Assumptions!$C$66 | G6: =Assumptions!$C$77 | H6: =E6*G6
B7: Engineering-heavy firms | C7: =Assumptions!$C$40 | D7: =Assumptions!$C$44 | E7: =C7*D7 | F7: =Assumptions!$C$69 | G7: =Assumptions!$C$78 | H7: =E7*G7
B8: Mid-size structured-hiring firms | C8: =Assumptions!$C$41 | D8: =Assumptions!$C$45 | E8: =C8*D8 | F8: =Assumptions!$C$72 | G8: =Assumptions!$C$79 | H8: =E8*G8
B9: SAM (focus-6, serviceable today) | E9: =SUM(E6:E8) | H9: =SUM(H6:H8)
B11: B. TAM (all geos where product works, at full ACV)
B12: Global gross-up = focus-6 / (focus-6 share of global)
B13: Segment | C13: Global entities | D13: % fit | E13: Serviceable accts | F13: ACV/acct ($) | G13: TAM value ($/yr)
B14: Tech recruiting agencies | C14: =Assumptions!$C$39/Assumptions!$C$98 | D14: =Assumptions!$C$43 | E14: =C14*D14 | F14: =Assumptions!$C$77 | G14: =E14*F14
B15: Engineering-heavy firms | C15: =Assumptions!$C$40/Assumptions!$C$98 | D15: =Assumptions!$C$44 | E15: =C15*D15 | F15: =Assumptions!$C$78 | G15: =E15*F15
B16: Mid-size structured-hiring firms | C16: =Assumptions!$C$41/Assumptions!$C$98 | D16: =Assumptions!$C$45 | E16: =C16*D16 | F16: =Assumptions!$C$79 | G16: =E16*F16
B17: TAM (global prize, full ACV) | G17: =SUM(G14:G16)
B19: C. SOM (3-year reachable) - two routes side by side
B20: CHANNEL ROUTE (partner portfolio - see Assumptions sec.7)
B21: Channel base accounts (portfolio, y3) | E21: =Assumptions!$G$89
B22: Attach scalar | E22: =Assumptions!$C$90
B23: Active channel accounts | E23: =E21*E22
B24: Channel revenue ($/yr, retention-adj) | E24: =E23*Assumptions!$C$80*Assumptions!$C$97
B26: DIRECT ROUTE (self-serve + sales-led) | E26: Year 3
B27: Serviceable SAM accounts | E27: =Build!$E$9
B28: 3-yr penetration | E28: =Assumptions!$C$92
B29: Active direct accounts | E29: =E27*E28
B30: Direct revenue ($/yr, retention-adj) | E30: =Build!$H$9*E28*Assumptions!$C$97
B31: Funnel cross-check: implied paid/yr | E31: =Assumptions!$C$93*12*Assumptions!$C$94*Assumptions!$C$95
B33: SOM (Year 3 = Channel + Direct) | E33: =E24+E30
B35: D. Revenue potential by stream (assessments + talent-DB)
B36: Tier | C36: Assessment rev ($/yr) | D36: Tests run / yr | E36: Talent-DB rev ($/yr) | F36: TOTAL revenue potential ($/yr)
B37: Full opportunity (TAM) | C37: =Build!$G$17 | D37: =C37/Assumptions!$C$61 | E37: =D37*Assumptions!$C$104*Assumptions!$C$105 | F37: =C37+E37
B38: Serviceable today (SAM) | C38: =Build!$H$9 | D38: =C38/Assumptions!$C$61 | E38: =D38*Assumptions!$C$104*Assumptions!$C$105 | F38: =C38+E38
B39: 3-yr reachable (SOM) | C39: =Build!$E$33 | D39: =C39/Assumptions!$C$61 | E39: =D39*Assumptions!$C$104*Assumptions!$C$105 | F39: =C39+E39
B41: E. Value delivered (tests run -> hires -> bad-hire cost addressed)
B42: Ring | C42: Accounts | D42: Tests run / yr | E42: Hires supported / yr | F42: Bad-hire $ exposure influenced | G42: Mitigable value to buyers ($)
B43: SOM (yr 3) | C43: =(Build!$E$23+Build!$E$29) | D43: =C43*Assumptions!$C$75 | E43: =D43/Assumptions!$C$101 | F43: =E43*Assumptions!$C$100 | G43: =F43*Assumptions!$C$102
B45: Notes: (1) MECE - agencies and the firms they serve are distinct buyers; agency tests cover client roles, in-house tests cover own roles, no double count. (2) Channel (Manatal, global) and Direct (focus-6) may overlap modestly; treated as additive (slightly optimistic) and flagged. (3) Value-delivered ring is buyer-side: $ exposure influenced and mitigable value are NOT market size - they show the value pool Invirtus serves, against which the SOM revenue captured (~$2.2M) is a tiny slice. (4) Hires = gross placements assessment touches; agencies place for many clients, so per-account hires run high.

Sheet Sensitivity
B2: INVIRTUS - Sensitivity
B3: SOM (Yr3) response to the three swing inputs. Tables recompute the SOM chain live from the axis values; non-swung drivers pull from Assumptions.
B5: Table 1: SOM (Yr3) - Channel tests/account vs PAYG price/test
B6: tests/acct \ $/test | C6: 10 | D6: 12.5 | E6: 15 | F6: 17.5 | G6: 20
B7: 100 | C7: =Assumptions!$G$89*Assumptions!$C$90*($B7*((Assumptions!$C$56*C$6+Assumptions!$C$57*C$6*(1-Assumptions!$C$48)+Assumptions!$C$58*C$6*(1-Assumptions!$C$49)+Assumptions!$C$59*C$6*(1-Assumptions!$C$50))/(Assumptions!$C$56+Assumptions!$C$57+Assumptions!$C$58+Assumptions!$C$59)))*Assumptions!$C$97+(((Assumptions!$C$39*Assumptions!$C$43*((Assumptions!$C$64*Assumptions!$C$65*Assumptions!$C$63)*((Assumptions!$C$56*C$6+Assumptions!$C$57*C$6*(1-Assumptions!$C$48)+Assumptions!$C$58*C$6*(1-Assumptions!$C$49)+Assumptions!$C$59*C$6*(1-Assumptions!$C$50))/(Assumptions!$C$56+Assumptions!$C$57+Assumptions!$C$58+Assumptions!$C$59))))+(Assumptions!$C$40*Assumptions!$C$44*((Assumptions!$C$67*Assumptions!$C$68*Assumptions!$C$63)*((Assumptions!$C$56*C$6+Assumptions!$C$57*C$6*(1-Assumptions!$C$48)+Assumptions!$C$58*C$6*(1-Assumptions!$C$49)+Assumptions!$C$59*C$6*(1-Assumptions!$C$50))/(Assumptions!$C$56+Assumptions!$C$57+Assumptions!$C$58+Assumptions!$C$59))))+(Assumptions!$C$41*Assumptions!$C$45*((Assumptions!$C$70*Assumptions!$C$71*Assumptions!$C$63)*((Assumptions!$C$56*C$6+Assumptions!$C$57*C$6*(1-Assumptions!$C$48)+Assumptions!$C$58*C$6*(1-Assumptions!$C$49)+Assumptions!$C$59*C$6*(1-Assumptions!$C$50))/(Assumptions!$C$56+Assumptions!$C$57+Assumptions!$C$58+Assumptions!$C$59)))))*Assumptions!$C$92*Assumptions!$C$97) | D7: =Assumptions!$G$89*Assumptions!$C$90*($B7*((Assumptions!$C$56*D$6+Assumptions!$C$57*D$6*(1-Assumptions!$C$48)+Assumptions!$C$58*D$6*(1-Assumptions!$C$49)+Assumptions!$C$59*D$6*(1-Assumptions!$C$50))/(Assumptions!$C$56+Assumptions!$C$57+Assumptions!$C$58+Assumptions!$C$59)))*Assumptions!$C$97+(((Assumptions!$C$39*Assumptions!$C$43*((Assumptions!$C$64*Assumptions!$C$65*Assumptions!$C$63)*((Assumptions!$C$56*D$6+Assumptions!$C$57*D$6*(1-Assumptions!$C$48)+Assumptions!$C$58*D$6*(1-Assumptions!$C$49)+Assumptions!$C$59*D$6*(1-Assumptions!$C$50))/(Assumptions!$C$56+Assumptions!$C$57+Assumptions!$C$58+Assumptions!$C$59))))+(Assumptions!$C$40*Assumptions!$C$44*((Assumptions!$C$67*Assumptions!$C$68*Assumptions!$C$63)*((Assumptions!$C$56*D$6+Assumptions!$C$57*D$6*(1-Assumptions!$C$48)+Assumptions!$C$58*D$6*(1-Assumptions!$C$49)+Assumptions!$C$59*D$6*(1-Assumptions!$C$50))/(Assumptions!$C$56+Assumptions!$C$57+Assumptions!$C$58+Assumptions!$C$59))))+(Assumptions!$C$41*Assumptions!$C$45*((Assumptions!$C$70*Assumptions!$C$71*Assumptions!$C$63)*((Assumptions!$C$56*D$6+Assumptions!$C$57*D$6*(1-Assumptions!$C$48)+Assumptions!$C$58*D$6*(1-Assumptions!$C$49)+Assumptions!$C$59*D$6*(1-Assumptions!$C$50))/(Assumptions!$C$56+Assumptions!$C$57+Assumptions!$C$58+Assumptions!$C$59)))))*Assumptions!$C$92*Assumptions!$C$97) | E7: =Assumptions!$G$89*Assumptions!$C$90*($B7*((Assumptions!$C$56*E$6+Assumptions!$C$57*E$6*(1-Assumptions!$C$48)+Assumptions!$C$58*E$6*(1-Assumptions!$C$49)+Assumptions!$C$59*E$6*(1-Assumptions!$C$50))/(Assumptions!$C$56+Assumptions!$C$57+Assumptions!$C$58+Assumptions!$C$59)))*Assumptions!$C$97+(((Assumptions!$C$39*Assumptions!$C$43*((Assumptions!$C$64*Assumptions!$C$65*Assumptions!$C$63)*((Assumptions!$C$56*E$6+Assumptions!$C$57*E$6*(1-Assumptions!$C$48)+Assumptions!$C$58*E$6*(1-Assumptions!$C$49)+Assumptions!$C$59*E$6*(1-Assumptions!$C$50))/(Assumptions!$C$56+Assumptions!$C$57+Assumptions!$C$58+Assumptions!$C$59))))+(Assumptions!$C$40*Assumptions!$C$44*((Assumptions!$C$67*Assumptions!$C$68*Assumptions!$C$63)*((Assumptions!$C$56*E$6+Assumptions!$C$57*E$6*(1-Assumptions!$C$48)+Assumptions!$C$58*E$6*(1-Assumptions!$C$49)+Assumptions!$C$59*E$6*(1-Assumptions!$C$50))/(Assumptions!$C$56+Assumptions!$C$57+Assumptions!$C$58+Assumptions!$C$59))))+(Assumptions!$C$41*Assumptions!$C$45*((Assumptions!$C$70*Assumptions!$C$71*Assumptions!$C$63)*((Assumptions!$C$56*E$6+Assumptions!$C$57*E$6*(1-Assumptions!$C$48)+Assumptions!$C$58*E$6*(1-Assumptions!$C$49)+Assumptions!$C$59*E$6*(1-Assumptions!$C$50))/(Assumptions!$C$56+Assumptions!$C$57+Assumptions!$C$58+Assumptions!$C$59)))))*Assumptions!$C$92*Assumptions!$C$97) | F7: =Assumptions!$G$89*Assumptions!$C$90*($B7*((Assumptions!$C$56*F$6+Assumptions!$C$57*F$6*(1-Assumptions!$C$48)+Assumptions!$C$58*F$6*(1-Assumptions!$C$49)+Assumptions!$C$59*F$6*(1-Assumptions!$C$50))/(Assumptions!$C$56+Assumptions!$C$57+Assumptions!$C$58+Assumptions!$C$59)))*Assumptions!$C$97+(((Assumptions!$C$39*Assumptions!$C$43*((Assumptions!$C$64*Assumptions!$C$65*Assumptions!$C$63)*((Assumptions!$C$56*F$6+Assumptions!$C$57*F$6*(1-Assumptions!$C$48)+Assumptions!$C$58*F$6*(1-Assumptions!$C$49)+Assumptions!$C$59*F$6*(1-Assumptions!$C$50))/(Assumptions!$C$56+Assumptions!$C$57+Assumptions!$C$58+Assumptions!$C$59))))+(Assumptions!$C$40*Assumptions!$C$44*((Assumptions!$C$67*Assumptions!$C$68*Assumptions!$C$63)*((Assumptions!$C$56*F$6+Assumptions!$C$57*F$6*(1-Assumptions!$C$48)+Assumptions!$C$58*F$6*(1-Assumptions!$C$49)+Assumptions!$C$59*F$6*(1-Assumptions!$C$50))/(Assumptions!$C$56+Assumptions!$C$57+Assumptions!$C$58+Assumptions!$C$59))))+(Assumptions!$C$41*Assumptions!$C$45*((Assumptions!$C$70*Assumptions!$C$71*Assumptions!$C$63)*((Assumptions!$C$56*F$6+Assumptions!$C$57*F$6*(1-Assumptions!$C$48)+Assumptions!$C$58*F$6*(1-Assumptions!$C$49)+Assumptions!$C$59*F$6*(1-Assumptions!$C$50))/(Assumptions!$C$56+Assumptions!$C$57+Assumptions!$C$58+Assumptions!$C$59)))))*Assumptions!$C$92*Assumptions!$C$97) | G7: =Assumptions!$G$89*Assumptions!$C$90*($B7*((Assumptions!$C$56*G$6+Assumptions!$C$57*G$6*(1-Assumptions!$C$48)+Assumptions!$C$58*G$6*(1-Assumptions!$C$49)+Assumptions!$C$59*G$6*(1-Assumptions!$C$50))/(Assumptions!$C$56+Assumptions!$C$57+Assumptions!$C$58+Assumptions!$C$59)))*Assumptions!$C$97+(((Assumptions!$C$39*Assumptions!$C$43*((Assumptions!$C$64*Assumptions!$C$65*Assumptions!$C$63)*((Assumptions!$C$56*G$6+Assumptions!$C$57*G$6*(1-Assumptions!$C$48)+Assumptions!$C$58*G$6*(1-Assumptions!$C$49)+Assumptions!$C$59*G$6*(1-Assumptions!$C$50))/(Assumptions!$C$56+Assumptions!$C$57+Assumptions!$C$58+Assumptions!$C$59))))+(Assumptions!$C$40*Assumptions!$C$44*((Assumptions!$C$67*Assumptions!$C$68*Assumptions!$C$63)*((Assumptions!$C$56*G$6+Assumptions!$C$57*G$6*(1-Assumptions!$C$48)+Assumptions!$C$58*G$6*(1-Assumptions!$C$49)+Assumptions!$C$59*G$6*(1-Assumptions!$C$50))/(Assumptions!$C$56+Assumptions!$C$57+Assumptions!$C$58+Assumptions!$C$59))))+(Assumptions!$C$41*Assumptions!$C$45*((Assumptions!$C$70*Assumptions!$C$71*Assumptions!$C$63)*((Assumptions!$C$56*G$6+Assumptions!$C$57*G$6*(1-Assumptions!$C$48)+Assumptions!$C$58*G$6*(1-Assumptions!$C$49)+Assumptions!$C$59*G$6*(1-Assumptions!$C$50))/(Assumptions!$C$56+Assumptions!$C$57+Assumptions!$C$58+Assumptions!$C$59)))))*Assumptions!$C$92*Assumptions!$C$97)
B8: 150 | C8: =Assumptions!$G$89*Assumptions!$C$90*($B8*((Assumptions!$C$56*C$6+Assumptions!$C$57*C$6*(1-Assumptions!$C$48)+Assumptions!$C$58*C$6*(1-Assumptions!$C$49)+Assumptions!$C$59*C$6*(1-Assumptions!$C$50))/(Assumptions!$C$56+Assumptions!$C$57+Assumptions!$C$58+Assumptions!$C$59)))*Assumptions!$C$97+(((Assumptions!$C$39*Assumptions!$C$43*((Assumptions!$C$64*Assumptions!$C$65*Assumptions!$C$63)*((Assumptions!$C$56*C$6+Assumptions!$C$57*C$6*(1-Assumptions!$C$48)+Assumptions!$C$58*C$6*(1-Assumptions!$C$49)+Assumptions!$C$59*C$6*(1-Assumptions!$C$50))/(Assumptions!$C$56+Assumptions!$C$57+Assumptions!$C$58+Assumptions!$C$59))))+(Assumptions!$C$40*Assumptions!$C$44*((Assumptions!$C$67*Assumptions!$C$68*Assumptions!$C$63)*((Assumptions!$C$56*C$6+Assumptions!$C$57*C$6*(1-Assumptions!$C$48)+Assumptions!$C$58*C$6*(1-Assumptions!$C$49)+Assumptions!$C$59*C$6*(1-Assumptions!$C$50))/(Assumptions!$C$56+Assumptions!$C$57+Assumptions!$C$58+Assumptions!$C$59))))+(Assumptions!$C$41*Assumptions!$C$45*((Assumptions!$C$70*Assumptions!$C$71*Assumptions!$C$63)*((Assumptions!$C$56*C$6+Assumptions!$C$57*C$6*(1-Assumptions!$C$48)+Assumptions!$C$58*C$6*(1-Assumptions!$C$49)+Assumptions!$C$59*C$6*(1-Assumptions!$C$50))/(Assumptions!$C$56+Assumptions!$C$57+Assumptions!$C$58+Assumptions!$C$59)))))*Assumptions!$C$92*Assumptions!$C$97) | D8: =Assumptions!$G$89*Assumptions!$C$90*($B8*((Assumptions!$C$56*D$6+Assumptions!$C$57*D$6*(1-Assumptions!$C$48)+Assumptions!$C$58*D$6*(1-Assumptions!$C$49)+Assumptions!$C$59*D$6*(1-Assumptions!$C$50))/(Assumptions!$C$56+Assumptions!$C$57+Assumptions!$C$58+Assumptions!$C$59)))*Assumptions!$C$97+(((Assumptions!$C$39*Assumptions!$C$43*((Assumptions!$C$64*Assumptions!$C$65*Assumptions!$C$63)*((Assumptions!$C$56*D$6+Assumptions!$C$57*D$6*(1-Assumptions!$C$48)+Assumptions!$C$58*D$6*(1-Assumptions!$C$49)+Assumptions!$C$59*D$6*(1-Assumptions!$C$50))/(Assumptions!$C$56+Assumptions!$C$57+Assumptions!$C$58+Assumptions!$C$59))))+(Assumptions!$C$40*Assumptions!$C$44*((Assumptions!$C$67*Assumptions!$C$68*Assumptions!$C$63)*((Assumptions!$C$56*D$6+Assumptions!$C$57*D$6*(1-Assumptions!$C$48)+Assumptions!$C$58*D$6*(1-Assumptions!$C$49)+Assumptions!$C$59*D$6*(1-Assumptions!$C$50))/(Assumptions!$C$56+Assumptions!$C$57+Assumptions!$C$58+Assumptions!$C$59))))+(Assumptions!$C$41*Assumptions!$C$45*((Assumptions!$C$70*Assumptions!$C$71*Assumptions!$C$63)*((Assumptions!$C$56*D$6+Assumptions!$C$57*D$6*(1-Assumptions!$C$48)+Assumptions!$C$58*D$6*(1-Assumptions!$C$49)+Assumptions!$C$59*D$6*(1-Assumptions!$C$50))/(Assumptions!$C$56+Assumptions!$C$57+Assumptions!$C$58+Assumptions!$C$59)))))*Assumptions!$C$92*Assumptions!$C$97) | E8: =Assumptions!$G$89*Assumptions!$C$90*($B8*((Assumptions!$C$56*E$6+Assumptions!$C$57*E$6*(1-Assumptions!$C$48)+Assumptions!$C$58*E$6*(1-Assumptions!$C$49)+Assumptions!$C$59*E$6*(1-Assumptions!$C$50))/(Assumptions!$C$56+Assumptions!$C$57+Assumptions!$C$58+Assumptions!$C$59)))*Assumptions!$C$97+(((Assumptions!$C$39*Assumptions!$C$43*((Assumptions!$C$64*Assumptions!$C$65*Assumptions!$C$63)*((Assumptions!$C$56*E$6+Assumptions!$C$57*E$6*(1-Assumptions!$C$48)+Assumptions!$C$58*E$6*(1-Assumptions!$C$49)+Assumptions!$C$59*E$6*(1-Assumptions!$C$50))/(Assumptions!$C$56+Assumptions!$C$57+Assumptions!$C$58+Assumptions!$C$59))))+(Assumptions!$C$40*Assumptions!$C$44*((Assumptions!$C$67*Assumptions!$C$68*Assumptions!$C$63)*((Assumptions!$C$56*E$6+Assumptions!$C$57*E$6*(1-Assumptions!$C$48)+Assumptions!$C$58*E$6*(1-Assumptions!$C$49)+Assumptions!$C$59*E$6*(1-Assumptions!$C$50))/(Assumptions!$C$56+Assumptions!$C$57+Assumptions!$C$58+Assumptions!$C$59))))+(Assumptions!$C$41*Assumptions!$C$45*((Assumptions!$C$70*Assumptions!$C$71*Assumptions!$C$63)*((Assumptions!$C$56*E$6+Assumptions!$C$57*E$6*(1-Assumptions!$C$48)+Assumptions!$C$58*E$6*(1-Assumptions!$C$49)+Assumptions!$C$59*E$6*(1-Assumptions!$C$50))/(Assumptions!$C$56+Assumptions!$C$57+Assumptions!$C$58+Assumptions!$C$59)))))*Assumptions!$C$92*Assumptions!$C$97) | F8: =Assumptions!$G$89*Assumptions!$C$90*($B8*((Assumptions!$C$56*F$6+Assumptions!$C$57*F$6*(1-Assumptions!$C$48)+Assumptions!$C$58*F$6*(1-Assumptions!$C$49)+Assumptions!$C$59*F$6*(1-Assumptions!$C$50))/(Assumptions!$C$56+Assumptions!$C$57+Assumptions!$C$58+Assumptions!$C$59)))*Assumptions!$C$97+(((Assumptions!$C$39*Assumptions!$C$43*((Assumptions!$C$64*Assumptions!$C$65*Assumptions!$C$63)*((Assumptions!$C$56*F$6+Assumptions!$C$57*F$6*(1-Assumptions!$C$48)+Assumptions!$C$58*F$6*(1-Assumptions!$C$49)+Assumptions!$C$59*F$6*(1-Assumptions!$C$50))/(Assumptions!$C$56+Assumptions!$C$57+Assumptions!$C$58+Assumptions!$C$59))))+(Assumptions!$C$40*Assumptions!$C$44*((Assumptions!$C$67*Assumptions!$C$68*Assumptions!$C$63)*((Assumptions!$C$56*F$6+Assumptions!$C$57*F$6*(1-Assumptions!$C$48)+Assumptions!$C$58*F$6*(1-Assumptions!$C$49)+Assumptions!$C$59*F$6*(1-Assumptions!$C$50))/(Assumptions!$C$56+Assumptions!$C$57+Assumptions!$C$58+Assumptions!$C$59))))+(Assumptions!$C$41*Assumptions!$C$45*((Assumptions!$C$70*Assumptions!$C$71*Assumptions!$C$63)*((Assumptions!$C$56*F$6+Assumptions!$C$57*F$6*(1-Assumptions!$C$48)+Assumptions!$C$58*F$6*(1-Assumptions!$C$49)+Assumptions!$C$59*F$6*(1-Assumptions!$C$50))/(Assumptions!$C$56+Assumptions!$C$57+Assumptions!$C$58+Assumptions!$C$59)))))*Assumptions!$C$92*Assumptions!$C$97) | G8: =Assumptions!$G$89*Assumptions!$C$90*($B8*((Assumptions!$C$56*G$6+Assumptions!$C$57*G$6*(1-Assumptions!$C$48)+Assumptions!$C$58*G$6*(1-Assumptions!$C$49)+Assumptions!$C$59*G$6*(1-Assumptions!$C$50))/(Assumptions!$C$56+Assumptions!$C$57+Assumptions!$C$58+Assumptions!$C$59)))*Assumptions!$C$97+(((Assumptions!$C$39*Assumptions!$C$43*((Assumptions!$C$64*Assumptions!$C$65*Assumptions!$C$63)*((Assumptions!$C$56*G$6+Assumptions!$C$57*G$6*(1-Assumptions!$C$48)+Assumptions!$C$58*G$6*(1-Assumptions!$C$49)+Assumptions!$C$59*G$6*(1-Assumptions!$C$50))/(Assumptions!$C$56+Assumptions!$C$57+Assumptions!$C$58+Assumptions!$C$59))))+(Assumptions!$C$40*Assumptions!$C$44*((Assumptions!$C$67*Assumptions!$C$68*Assumptions!$C$63)*((Assumptions!$C$56*G$6+Assumptions!$C$57*G$6*(1-Assumptions!$C$48)+Assumptions!$C$58*G$6*(1-Assumptions!$C$49)+Assumptions!$C$59*G$6*(1-Assumptions!$C$50))/(Assumptions!$C$56+Assumptions!$C$57+Assumptions!$C$58+Assumptions!$C$59))))+(Assumptions!$C$41*Assumptions!$C$45*((Assumptions!$C$70*Assumptions!$C$71*Assumptions!$C$63)*((Assumptions!$C$56*G$6+Assumptions!$C$57*G$6*(1-Assumptions!$C$48)+Assumptions!$C$58*G$6*(1-Assumptions!$C$49)+Assumptions!$C$59*G$6*(1-Assumptions!$C$50))/(Assumptions!$C$56+Assumptions!$C$57+Assumptions!$C$58+Assumptions!$C$59)))))*Assumptions!$C$92*Assumptions!$C$97)
B9: 200 | C9: =Assumptions!$G$89*Assumptions!$C$90*($B9*((Assumptions!$C$56*C$6+Assumptions!$C$57*C$6*(1-Assumptions!$C$48)+Assumptions!$C$58*C$6*(1-Assumptions!$C$49)+Assumptions!$C$59*C$6*(1-Assumptions!$C$50))/(Assumptions!$C$56+Assumptions!$C$57+Assumptions!$C$58+Assumptions!$C$59)))*Assumptions!$C$97+(((Assumptions!$C$39*Assumptions!$C$43*((Assumptions!$C$64*Assumptions!$C$65*Assumptions!$C$63)*((Assumptions!$C$56*C$6+Assumptions!$C$57*C$6*(1-Assumptions!$C$48)+Assumptions!$C$58*C$6*(1-Assumptions!$C$49)+Assumptions!$C$59*C$6*(1-Assumptions!$C$50))/(Assumptions!$C$56+Assumptions!$C$57+Assumptions!$C$58+Assumptions!$C$59))))+(Assumptions!$C$40*Assumptions!$C$44*((Assumptions!$C$67*Assumptions!$C$68*Assumptions!$C$63)*((Assumptions!$C$56*C$6+Assumptions!$C$57*C$6*(1-Assumptions!$C$48)+Assumptions!$C$58*C$6*(1-Assumptions!$C$49)+Assumptions!$C$59*C$6*(1-Assumptions!$C$50))/(Assumptions!$C$56+Assumptions!$C$57+Assumptions!$C$58+Assumptions!$C$59))))+(Assumptions!$C$41*Assumptions!$C$45*((Assumptions!$C$70*Assumptions!$C$71*Assumptions!$C$63)*((Assumptions!$C$56*C$6+Assumptions!$C$57*C$6*(1-Assumptions!$C$48)+Assumptions!$C$58*C$6*(1-Assumptions!$C$49)+Assumptions!$C$59*C$6*(1-Assumptions!$C$50))/(Assumptions!$C$56+Assumptions!$C$57+Assumptions!$C$58+Assumptions!$C$59)))))*Assumptions!$C$92*Assumptions!$C$97) | D9: =Assumptions!$G$89*Assumptions!$C$90*($B9*((Assumptions!$C$56*D$6+Assumptions!$C$57*D$6*(1-Assumptions!$C$48)+Assumptions!$C$58*D$6*(1-Assumptions!$C$49)+Assumptions!$C$59*D$6*(1-Assumptions!$C$50))/(Assumptions!$C$56+Assumptions!$C$57+Assumptions!$C$58+Assumptions!$C$59)))*Assumptions!$C$97+(((Assumptions!$C$39*Assumptions!$C$43*((Assumptions!$C$64*Assumptions!$C$65*Assumptions!$C$63)*((Assumptions!$C$56*D$6+Assumptions!$C$57*D$6*(1-Assumptions!$C$48)+Assumptions!$C$58*D$6*(1-Assumptions!$C$49)+Assumptions!$C$59*D$6*(1-Assumptions!$C$50))/(Assumptions!$C$56+Assumptions!$C$57+Assumptions!$C$58+Assumptions!$C$59))))+(Assumptions!$C$40*Assumptions!$C$44*((Assumptions!$C$67*Assumptions!$C$68*Assumptions!$C$63)*((Assumptions!$C$56*D$6+Assumptions!$C$57*D$6*(1-Assumptions!$C$48)+Assumptions!$C$58*D$6*(1-Assumptions!$C$49)+Assumptions!$C$59*D$6*(1-Assumptions!$C$50))/(Assumptions!$C$56+Assumptions!$C$57+Assumptions!$C$58+Assumptions!$C$59))))+(Assumptions!$C$41*Assumptions!$C$45*((Assumptions!$C$70*Assumptions!$C$71*Assumptions!$C$63)*((Assumptions!$C$56*D$6+Assumptions!$C$57*D$6*(1-Assumptions!$C$48)+Assumptions!$C$58*D$6*(1-Assumptions!$C$49)+Assumptions!$C$59*D$6*(1-Assumptions!$C$50))/(Assumptions!$C$56+Assumptions!$C$57+Assumptions!$C$58+Assumptions!$C$59)))))*Assumptions!$C$92*Assumptions!$C$97) | E9: =Assumptions!$G$89*Assumptions!$C$90*($B9*((Assumptions!$C$56*E$6+Assumptions!$C$57*E$6*(1-Assumptions!$C$48)+Assumptions!$C$58*E$6*(1-Assumptions!$C$49)+Assumptions!$C$59*E$6*(1-Assumptions!$C$50))/(Assumptions!$C$56+Assumptions!$C$57+Assumptions!$C$58+Assumptions!$C$59)))*Assumptions!$C$97+(((Assumptions!$C$39*Assumptions!$C$43*((Assumptions!$C$64*Assumptions!$C$65*Assumptions!$C$63)*((Assumptions!$C$56*E$6+Assumptions!$C$57*E$6*(1-Assumptions!$C$48)+Assumptions!$C$58*E$6*(1-Assumptions!$C$49)+Assumptions!$C$59*E$6*(1-Assumptions!$C$50))/(Assumptions!$C$56+Assumptions!$C$57+Assumptions!$C$58+Assumptions!$C$59))))+(Assumptions!$C$40*Assumptions!$C$44*((Assumptions!$C$67*Assumptions!$C$68*Assumptions!$C$63)*((Assumptions!$C$56*E$6+Assumptions!$C$57*E$6*(1-Assumptions!$C$48)+Assumptions!$C$58*E$6*(1-Assumptions!$C$49)+Assumptions!$C$59*E$6*(1-Assumptions!$C$50))/(Assumptions!$C$56+Assumptions!$C$57+Assumptions!$C$58+Assumptions!$C$59))))+(Assumptions!$C$41*Assumptions!$C$45*((Assumptions!$C$70*Assumptions!$C$71*Assumptions!$C$63)*((Assumptions!$C$56*E$6+Assumptions!$C$57*E$6*(1-Assumptions!$C$48)+Assumptions!$C$58*E$6*(1-Assumptions!$C$49)+Assumptions!$C$59*E$6*(1-Assumptions!$C$50))/(Assumptions!$C$56+Assumptions!$C$57+Assumptions!$C$58+Assumptions!$C$59)))))*Assumptions!$C$92*Assumptions!$C$97) | F9: =Assumptions!$G$89*Assumptions!$C$90*($B9*((Assumptions!$C$56*F$6+Assumptions!$C$57*F$6*(1-Assumptions!$C$48)+Assumptions!$C$58*F$6*(1-Assumptions!$C$49)+Assumptions!$C$59*F$6*(1-Assumptions!$C$50))/(Assumptions!$C$56+Assumptions!$C$57+Assumptions!$C$58+Assumptions!$C$59)))*Assumptions!$C$97+(((Assumptions!$C$39*Assumptions!$C$43*((Assumptions!$C$64*Assumptions!$C$65*Assumptions!$C$63)*((Assumptions!$C$56*F$6+Assumptions!$C$57*F$6*(1-Assumptions!$C$48)+Assumptions!$C$58*F$6*(1-Assumptions!$C$49)+Assumptions!$C$59*F$6*(1-Assumptions!$C$50))/(Assumptions!$C$56+Assumptions!$C$57+Assumptions!$C$58+Assumptions!$C$59))))+(Assumptions!$C$40*Assumptions!$C$44*((Assumptions!$C$67*Assumptions!$C$68*Assumptions!$C$63)*((Assumptions!$C$56*F$6+Assumptions!$C$57*F$6*(1-Assumptions!$C$48)+Assumptions!$C$58*F$6*(1-Assumptions!$C$49)+Assumptions!$C$59*F$6*(1-Assumptions!$C$50))/(Assumptions!$C$56+Assumptions!$C$57+Assumptions!$C$58+Assumptions!$C$59))))+(Assumptions!$C$41*Assumptions!$C$45*((Assumptions!$C$70*Assumptions!$C$71*Assumptions!$C$63)*((Assumptions!$C$56*F$6+Assumptions!$C$57*F$6*(1-Assumptions!$C$48)+Assumptions!$C$58*F$6*(1-Assumptions!$C$49)+Assumptions!$C$59*F$6*(1-Assumptions!$C$50))/(Assumptions!$C$56+Assumptions!$C$57+Assumptions!$C$58+Assumptions!$C$59)))))*Assumptions!$C$92*Assumptions!$C$97) | G9: =Assumptions!$G$89*Assumptions!$C$90*($B9*((Assumptions!$C$56*G$6+Assumptions!$C$57*G$6*(1-Assumptions!$C$48)+Assumptions!$C$58*G$6*(1-Assumptions!$C$49)+Assumptions!$C$59*G$6*(1-Assumptions!$C$50))/(Assumptions!$C$56+Assumptions!$C$57+Assumptions!$C$58+Assumptions!$C$59)))*Assumptions!$C$97+(((Assumptions!$C$39*Assumptions!$C$43*((Assumptions!$C$64*Assumptions!$C$65*Assumptions!$C$63)*((Assumptions!$C$56*G$6+Assumptions!$C$57*G$6*(1-Assumptions!$C$48)+Assumptions!$C$58*G$6*(1-Assumptions!$C$49)+Assumptions!$C$59*G$6*(1-Assumptions!$C$50))/(Assumptions!$C$56+Assumptions!$C$57+Assumptions!$C$58+Assumptions!$C$59))))+(Assumptions!$C$40*Assumptions!$C$44*((Assumptions!$C$67*Assumptions!$C$68*Assumptions!$C$63)*((Assumptions!$C$56*G$6+Assumptions!$C$57*G$6*(1-Assumptions!$C$48)+Assumptions!$C$58*G$6*(1-Assumptions!$C$49)+Assumptions!$C$59*G$6*(1-Assumptions!$C$50))/(Assumptions!$C$56+Assumptions!$C$57+Assumptions!$C$58+Assumptions!$C$59))))+(Assumptions!$C$41*Assumptions!$C$45*((Assumptions!$C$70*Assumptions!$C$71*Assumptions!$C$63)*((Assumptions!$C$56*G$6+Assumptions!$C$57*G$6*(1-Assumptions!$C$48)+Assumptions!$C$58*G$6*(1-Assumptions!$C$49)+Assumptions!$C$59*G$6*(1-Assumptions!$C$50))/(Assumptions!$C$56+Assumptions!$C$57+Assumptions!$C$58+Assumptions!$C$59)))))*Assumptions!$C$92*Assumptions!$C$97)
B10: 250 | C10: =Assumptions!$G$89*Assumptions!$C$90*($B10*((Assumptions!$C$56*C$6+Assumptions!$C$57*C$6*(1-Assumptions!$C$48)+Assumptions!$C$58*C$6*(1-Assumptions!$C$49)+Assumptions!$C$59*C$6*(1-Assumptions!$C$50))/(Assumptions!$C$56+Assumptions!$C$57+Assumptions!$C$58+Assumptions!$C$59)))*Assumptions!$C$97+(((Assumptions!$C$39*Assumptions!$C$43*((Assumptions!$C$64*Assumptions!$C$65*Assumptions!$C$63)*((Assumptions!$C$56*C$6+Assumptions!$C$57*C$6*(1-Assumptions!$C$48)+Assumptions!$C$58*C$6*(1-Assumptions!$C$49)+Assumptions!$C$59*C$6*(1-Assumptions!$C$50))/(Assumptions!$C$56+Assumptions!$C$57+Assumptions!$C$58+Assumptions!$C$59))))+(Assumptions!$C$40*Assumptions!$C$44*((Assumptions!$C$67*Assumptions!$C$68*Assumptions!$C$63)*((Assumptions!$C$56*C$6+Assumptions!$C$57*C$6*(1-Assumptions!$C$48)+Assumptions!$C$58*C$6*(1-Assumptions!$C$49)+Assumptions!$C$59*C$6*(1-Assumptions!$C$50))/(Assumptions!$C$56+Assumptions!$C$57+Assumptions!$C$58+Assumptions!$C$59))))+(Assumptions!$C$41*Assumptions!$C$45*((Assumptions!$C$70*Assumptions!$C$71*Assumptions!$C$63)*((Assumptions!$C$56*C$6+Assumptions!$C$57*C$6*(1-Assumptions!$C$48)+Assumptions!$C$58*C$6*(1-Assumptions!$C$49)+Assumptions!$C$59*C$6*(1-Assumptions!$C$50))/(Assumptions!$C$56+Assumptions!$C$57+Assumptions!$C$58+Assumptions!$C$59)))))*Assumptions!$C$92*Assumptions!$C$97) | D10: =Assumptions!$G$89*Assumptions!$C$90*($B10*((Assumptions!$C$56*D$6+Assumptions!$C$57*D$6*(1-Assumptions!$C$48)+Assumptions!$C$58*D$6*(1-Assumptions!$C$49)+Assumptions!$C$59*D$6*(1-Assumptions!$C$50))/(Assumptions!$C$56+Assumptions!$C$57+Assumptions!$C$58+Assumptions!$C$59)))*Assumptions!$C$97+(((Assumptions!$C$39*Assumptions!$C$43*((Assumptions!$C$64*Assumptions!$C$65*Assumptions!$C$63)*((Assumptions!$C$56*D$6+Assumptions!$C$57*D$6*(1-Assumptions!$C$48)+Assumptions!$C$58*D$6*(1-Assumptions!$C$49)+Assumptions!$C$59*D$6*(1-Assumptions!$C$50))/(Assumptions!$C$56+Assumptions!$C$57+Assumptions!$C$58+Assumptions!$C$59))))+(Assumptions!$C$40*Assumptions!$C$44*((Assumptions!$C$67*Assumptions!$C$68*Assumptions!$C$63)*((Assumptions!$C$56*D$6+Assumptions!$C$57*D$6*(1-Assumptions!$C$48)+Assumptions!$C$58*D$6*(1-Assumptions!$C$49)+Assumptions!$C$59*D$6*(1-Assumptions!$C$50))/(Assumptions!$C$56+Assumptions!$C$57+Assumptions!$C$58+Assumptions!$C$59))))+(Assumptions!$C$41*Assumptions!$C$45*((Assumptions!$C$70*Assumptions!$C$71*Assumptions!$C$63)*((Assumptions!$C$56*D$6+Assumptions!$C$57*D$6*(1-Assumptions!$C$48)+Assumptions!$C$58*D$6*(1-Assumptions!$C$49)+Assumptions!$C$59*D$6*(1-Assumptions!$C$50))/(Assumptions!$C$56+Assumptions!$C$57+Assumptions!$C$58+Assumptions!$C$59)))))*Assumptions!$C$92*Assumptions!$C$97) | E10: =Assumptions!$G$89*Assumptions!$C$90*($B10*((Assumptions!$C$56*E$6+Assumptions!$C$57*E$6*(1-Assumptions!$C$48)+Assumptions!$C$58*E$6*(1-Assumptions!$C$49)+Assumptions!$C$59*E$6*(1-Assumptions!$C$50))/(Assumptions!$C$56+Assumptions!$C$57+Assumptions!$C$58+Assumptions!$C$59)))*Assumptions!$C$97+(((Assumptions!$C$39*Assumptions!$C$43*((Assumptions!$C$64*Assumptions!$C$65*Assumptions!$C$63)*((Assumptions!$C$56*E$6+Assumptions!$C$57*E$6*(1-Assumptions!$C$48)+Assumptions!$C$58*E$6*(1-Assumptions!$C$49)+Assumptions!$C$59*E$6*(1-Assumptions!$C$50))/(Assumptions!$C$56+Assumptions!$C$57+Assumptions!$C$58+Assumptions!$C$59))))+(Assumptions!$C$40*Assumptions!$C$44*((Assumptions!$C$67*Assumptions!$C$68*Assumptions!$C$63)*((Assumptions!$C$56*E$6+Assumptions!$C$57*E$6*(1-Assumptions!$C$48)+Assumptions!$C$58*E$6*(1-Assumptions!$C$49)+Assumptions!$C$59*E$6*(1-Assumptions!$C$50))/(Assumptions!$C$56+Assumptions!$C$57+Assumptions!$C$58+Assumptions!$C$59))))+(Assumptions!$C$41*Assumptions!$C$45*((Assumptions!$C$70*Assumptions!$C$71*Assumptions!$C$63)*((Assumptions!$C$56*E$6+Assumptions!$C$57*E$6*(1-Assumptions!$C$48)+Assumptions!$C$58*E$6*(1-Assumptions!$C$49)+Assumptions!$C$59*E$6*(1-Assumptions!$C$50))/(Assumptions!$C$56+Assumptions!$C$57+Assumptions!$C$58+Assumptions!$C$59)))))*Assumptions!$C$92*Assumptions!$C$97) | F10: =Assumptions!$G$89*Assumptions!$C$90*($B10*((Assumptions!$C$56*F$6+Assumptions!$C$57*F$6*(1-Assumptions!$C$48)+Assumptions!$C$58*F$6*(1-Assumptions!$C$49)+Assumptions!$C$59*F$6*(1-Assumptions!$C$50))/(Assumptions!$C$56+Assumptions!$C$57+Assumptions!$C$58+Assumptions!$C$59)))*Assumptions!$C$97+(((Assumptions!$C$39*Assumptions!$C$43*((Assumptions!$C$64*Assumptions!$C$65*Assumptions!$C$63)*((Assumptions!$C$56*F$6+Assumptions!$C$57*F$6*(1-Assumptions!$C$48)+Assumptions!$C$58*F$6*(1-Assumptions!$C$49)+Assumptions!$C$59*F$6*(1-Assumptions!$C$50))/(Assumptions!$C$56+Assumptions!$C$57+Assumptions!$C$58+Assumptions!$C$59))))+(Assumptions!$C$40*Assumptions!$C$44*((Assumptions!$C$67*Assumptions!$C$68*Assumptions!$C$63)*((Assumptions!$C$56*F$6+Assumptions!$C$57*F$6*(1-Assumptions!$C$48)+Assumptions!$C$58*F$6*(1-Assumptions!$C$49)+Assumptions!$C$59*F$6*(1-Assumptions!$C$50))/(Assumptions!$C$56+Assumptions!$C$57+Assumptions!$C$58+Assumptions!$C$59))))+(Assumptions!$C$41*Assumptions!$C$45*((Assumptions!$C$70*Assumptions!$C$71*Assumptions!$C$63)*((Assumptions!$C$56*F$6+Assumptions!$C$57*F$6*(1-Assumptions!$C$48)+Assumptions!$C$58*F$6*(1-Assumptions!$C$49)+Assumptions!$C$59*F$6*(1-Assumptions!$C$50))/(Assumptions!$C$56+Assumptions!$C$57+Assumptions!$C$58+Assumptions!$C$59)))))*Assumptions!$C$92*Assumptions!$C$97) | G10: =Assumptions!$G$89*Assumptions!$C$90*($B10*((Assumptions!$C$56*G$6+Assumptions!$C$57*G$6*(1-Assumptions!$C$48)+Assumptions!$C$58*G$6*(1-Assumptions!$C$49)+Assumptions!$C$59*G$6*(1-Assumptions!$C$50))/(Assumptions!$C$56+Assumptions!$C$57+Assumptions!$C$58+Assumptions!$C$59)))*Assumptions!$C$97+(((Assumptions!$C$39*Assumptions!$C$43*((Assumptions!$C$64*Assumptions!$C$65*Assumptions!$C$63)*((Assumptions!$C$56*G$6+Assumptions!$C$57*G$6*(1-Assumptions!$C$48)+Assumptions!$C$58*G$6*(1-Assumptions!$C$49)+Assumptions!$C$59*G$6*(1-Assumptions!$C$50))/(Assumptions!$C$56+Assumptions!$C$57+Assumptions!$C$58+Assumptions!$C$59))))+(Assumptions!$C$40*Assumptions!$C$44*((Assumptions!$C$67*Assumptions!$C$68*Assumptions!$C$63)*((Assumptions!$C$56*G$6+Assumptions!$C$57*G$6*(1-Assumptions!$C$48)+Assumptions!$C$58*G$6*(1-Assumptions!$C$49)+Assumptions!$C$59*G$6*(1-Assumptions!$C$50))/(Assumptions!$C$56+Assumptions!$C$57+Assumptions!$C$58+Assumptions!$C$59))))+(Assumptions!$C$41*Assumptions!$C$45*((Assumptions!$C$70*Assumptions!$C$71*Assumptions!$C$63)*((Assumptions!$C$56*G$6+Assumptions!$C$57*G$6*(1-Assumptions!$C$48)+Assumptions!$C$58*G$6*(1-Assumptions!$C$49)+Assumptions!$C$59*G$6*(1-Assumptions!$C$50))/(Assumptions!$C$56+Assumptions!$C$57+Assumptions!$C$58+Assumptions!$C$59)))))*Assumptions!$C$92*Assumptions!$C$97)
B11: 300 | C11: =Assumptions!$G$89*Assumptions!$C$90*($B11*((Assumptions!$C$56*C$6+Assumptions!$C$57*C$6*(1-Assumptions!$C$48)+Assumptions!$C$58*C$6*(1-Assumptions!$C$49)+Assumptions!$C$59*C$6*(1-Assumptions!$C$50))/(Assumptions!$C$56+Assumptions!$C$57+Assumptions!$C$58+Assumptions!$C$59)))*Assumptions!$C$97+(((Assumptions!$C$39*Assumptions!$C$43*((Assumptions!$C$64*Assumptions!$C$65*Assumptions!$C$63)*((Assumptions!$C$56*C$6+Assumptions!$C$57*C$6*(1-Assumptions!$C$48)+Assumptions!$C$58*C$6*(1-Assumptions!$C$49)+Assumptions!$C$59*C$6*(1-Assumptions!$C$50))/(Assumptions!$C$56+Assumptions!$C$57+Assumptions!$C$58+Assumptions!$C$59))))+(Assumptions!$C$40*Assumptions!$C$44*((Assumptions!$C$67*Assumptions!$C$68*Assumptions!$C$63)*((Assumptions!$C$56*C$6+Assumptions!$C$57*C$6*(1-Assumptions!$C$48)+Assumptions!$C$58*C$6*(1-Assumptions!$C$49)+Assumptions!$C$59*C$6*(1-Assumptions!$C$50))/(Assumptions!$C$56+Assumptions!$C$57+Assumptions!$C$58+Assumptions!$C$59))))+(Assumptions!$C$41*Assumptions!$C$45*((Assumptions!$C$70*Assumptions!$C$71*Assumptions!$C$63)*((Assumptions!$C$56*C$6+Assumptions!$C$57*C$6*(1-Assumptions!$C$48)+Assumptions!$C$58*C$6*(1-Assumptions!$C$49)+Assumptions!$C$59*C$6*(1-Assumptions!$C$50))/(Assumptions!$C$56+Assumptions!$C$57+Assumptions!$C$58+Assumptions!$C$59)))))*Assumptions!$C$92*Assumptions!$C$97) | D11: =Assumptions!$G$89*Assumptions!$C$90*($B11*((Assumptions!$C$56*D$6+Assumptions!$C$57*D$6*(1-Assumptions!$C$48)+Assumptions!$C$58*D$6*(1-Assumptions!$C$49)+Assumptions!$C$59*D$6*(1-Assumptions!$C$50))/(Assumptions!$C$56+Assumptions!$C$57+Assumptions!$C$58+Assumptions!$C$59)))*Assumptions!$C$97+(((Assumptions!$C$39*Assumptions!$C$43*((Assumptions!$C$64*Assumptions!$C$65*Assumptions!$C$63)*((Assumptions!$C$56*D$6+Assumptions!$C$57*D$6*(1-Assumptions!$C$48)+Assumptions!$C$58*D$6*(1-Assumptions!$C$49)+Assumptions!$C$59*D$6*(1-Assumptions!$C$50))/(Assumptions!$C$56+Assumptions!$C$57+Assumptions!$C$58+Assumptions!$C$59))))+(Assumptions!$C$40*Assumptions!$C$44*((Assumptions!$C$67*Assumptions!$C$68*Assumptions!$C$63)*((Assumptions!$C$56*D$6+Assumptions!$C$57*D$6*(1-Assumptions!$C$48)+Assumptions!$C$58*D$6*(1-Assumptions!$C$49)+Assumptions!$C$59*D$6*(1-Assumptions!$C$50))/(Assumptions!$C$56+Assumptions!$C$57+Assumptions!$C$58+Assumptions!$C$59))))+(Assumptions!$C$41*Assumptions!$C$45*((Assumptions!$C$70*Assumptions!$C$71*Assumptions!$C$63)*((Assumptions!$C$56*D$6+Assumptions!$C$57*D$6*(1-Assumptions!$C$48)+Assumptions!$C$58*D$6*(1-Assumptions!$C$49)+Assumptions!$C$59*D$6*(1-Assumptions!$C$50))/(Assumptions!$C$56+Assumptions!$C$57+Assumptions!$C$58+Assumptions!$C$59)))))*Assumptions!$C$92*Assumptions!$C$97) | E11: =Assumptions!$G$89*Assumptions!$C$90*($B11*((Assumptions!$C$56*E$6+Assumptions!$C$57*E$6*(1-Assumptions!$C$48)+Assumptions!$C$58*E$6*(1-Assumptions!$C$49)+Assumptions!$C$59*E$6*(1-Assumptions!$C$50))/(Assumptions!$C$56+Assumptions!$C$57+Assumptions!$C$58+Assumptions!$C$59)))*Assumptions!$C$97+(((Assumptions!$C$39*Assumptions!$C$43*((Assumptions!$C$64*Assumptions!$C$65*Assumptions!$C$63)*((Assumptions!$C$56*E$6+Assumptions!$C$57*E$6*(1-Assumptions!$C$48)+Assumptions!$C$58*E$6*(1-Assumptions!$C$49)+Assumptions!$C$59*E$6*(1-Assumptions!$C$50))/(Assumptions!$C$56+Assumptions!$C$57+Assumptions!$C$58+Assumptions!$C$59))))+(Assumptions!$C$40*Assumptions!$C$44*((Assumptions!$C$67*Assumptions!$C$68*Assumptions!$C$63)*((Assumptions!$C$56*E$6+Assumptions!$C$57*E$6*(1-Assumptions!$C$48)+Assumptions!$C$58*E$6*(1-Assumptions!$C$49)+Assumptions!$C$59*E$6*(1-Assumptions!$C$50))/(Assumptions!$C$56+Assumptions!$C$57+Assumptions!$C$58+Assumptions!$C$59))))+(Assumptions!$C$41*Assumptions!$C$45*((Assumptions!$C$70*Assumptions!$C$71*Assumptions!$C$63)*((Assumptions!$C$56*E$6+Assumptions!$C$57*E$6*(1-Assumptions!$C$48)+Assumptions!$C$58*E$6*(1-Assumptions!$C$49)+Assumptions!$C$59*E$6*(1-Assumptions!$C$50))/(Assumptions!$C$56+Assumptions!$C$57+Assumptions!$C$58+Assumptions!$C$59)))))*Assumptions!$C$92*Assumptions!$C$97) | F11: =Assumptions!$G$89*Assumptions!$C$90*($B11*((Assumptions!$C$56*F$6+Assumptions!$C$57*F$6*(1-Assumptions!$C$48)+Assumptions!$C$58*F$6*(1-Assumptions!$C$49)+Assumptions!$C$59*F$6*(1-Assumptions!$C$50))/(Assumptions!$C$56+Assumptions!$C$57+Assumptions!$C$58+Assumptions!$C$59)))*Assumptions!$C$97+(((Assumptions!$C$39*Assumptions!$C$43*((Assumptions!$C$64*Assumptions!$C$65*Assumptions!$C$63)*((Assumptions!$C$56*F$6+Assumptions!$C$57*F$6*(1-Assumptions!$C$48)+Assumptions!$C$58*F$6*(1-Assumptions!$C$49)+Assumptions!$C$59*F$6*(1-Assumptions!$C$50))/(Assumptions!$C$56+Assumptions!$C$57+Assumptions!$C$58+Assumptions!$C$59))))+(Assumptions!$C$40*Assumptions!$C$44*((Assumptions!$C$67*Assumptions!$C$68*Assumptions!$C$63)*((Assumptions!$C$56*F$6+Assumptions!$C$57*F$6*(1-Assumptions!$C$48)+Assumptions!$C$58*F$6*(1-Assumptions!$C$49)+Assumptions!$C$59*F$6*(1-Assumptions!$C$50))/(Assumptions!$C$56+Assumptions!$C$57+Assumptions!$C$58+Assumptions!$C$59))))+(Assumptions!$C$41*Assumptions!$C$45*((Assumptions!$C$70*Assumptions!$C$71*Assumptions!$C$63)*((Assumptions!$C$56*F$6+Assumptions!$C$57*F$6*(1-Assumptions!$C$48)+Assumptions!$C$58*F$6*(1-Assumptions!$C$49)+Assumptions!$C$59*F$6*(1-Assumptions!$C$50))/(Assumptions!$C$56+Assumptions!$C$57+Assumptions!$C$58+Assumptions!$C$59)))))*Assumptions!$C$92*Assumptions!$C$97) | G11: =Assumptions!$G$89*Assumptions!$C$90*($B11*((Assumptions!$C$56*G$6+Assumptions!$C$57*G$6*(1-Assumptions!$C$48)+Assumptions!$C$58*G$6*(1-Assumptions!$C$49)+Assumptions!$C$59*G$6*(1-Assumptions!$C$50))/(Assumptions!$C$56+Assumptions!$C$57+Assumptions!$C$58+Assumptions!$C$59)))*Assumptions!$C$97+(((Assumptions!$C$39*Assumptions!$C$43*((Assumptions!$C$64*Assumptions!$C$65*Assumptions!$C$63)*((Assumptions!$C$56*G$6+Assumptions!$C$57*G$6*(1-Assumptions!$C$48)+Assumptions!$C$58*G$6*(1-Assumptions!$C$49)+Assumptions!$C$59*G$6*(1-Assumptions!$C$50))/(Assumptions!$C$56+Assumptions!$C$57+Assumptions!$C$58+Assumptions!$C$59))))+(Assumptions!$C$40*Assumptions!$C$44*((Assumptions!$C$67*Assumptions!$C$68*Assumptions!$C$63)*((Assumptions!$C$56*G$6+Assumptions!$C$57*G$6*(1-Assumptions!$C$48)+Assumptions!$C$58*G$6*(1-Assumptions!$C$49)+Assumptions!$C$59*G$6*(1-Assumptions!$C$50))/(Assumptions!$C$56+Assumptions!$C$57+Assumptions!$C$58+Assumptions!$C$59))))+(Assumptions!$C$41*Assumptions!$C$45*((Assumptions!$C$70*Assumptions!$C$71*Assumptions!$C$63)*((Assumptions!$C$56*G$6+Assumptions!$C$57*G$6*(1-Assumptions!$C$48)+Assumptions!$C$58*G$6*(1-Assumptions!$C$49)+Assumptions!$C$59*G$6*(1-Assumptions!$C$50))/(Assumptions!$C$56+Assumptions!$C$57+Assumptions!$C$58+Assumptions!$C$59)))))*Assumptions!$C$92*Assumptions!$C$97)
B13: Table 2: SOM (Yr3) - Channel attach scalar vs Channel tests/account
B14: attach x \ tests/acct | C14: 100 | D14: 150 | E14: 200 | F14: 250 | G14: 300
B15: 0.5 | C15: =Assumptions!$G$89*$B15*(C$14*((Assumptions!$C$56*Assumptions!$C$47+Assumptions!$C$57*Assumptions!$C$47*(1-Assumptions!$C$48)+Assumptions!$C$58*Assumptions!$C$47*(1-Assumptions!$C$49)+Assumptions!$C$59*Assumptions!$C$47*(1-Assumptions!$C$50))/(Assumptions!$C$56+Assumptions!$C$57+Assumptions!$C$58+Assumptions!$C$59)))*Assumptions!$C$97+(((Assumptions!$C$39*Assumptions!$C$43*((Assumptions!$C$64*Assumptions!$C$65*Assumptions!$C$63)*((Assumptions!$C$56*Assumptions!$C$47+Assumptions!$C$57*Assumptions!$C$47*(1-Assumptions!$C$48)+Assumptions!$C$58*Assumptions!$C$47*(1-Assumptions!$C$49)+Assumptions!$C$59*Assumptions!$C$47*(1-Assumptions!$C$50))/(Assumptions!$C$56+Assumptions!$C$57+Assumptions!$C$58+Assumptions!$C$59))))+(Assumptions!$C$40*Assumptions!$C$44*((Assumptions!$C$67*Assumptions!$C$68*Assumptions!$C$63)*((Assumptions!$C$56*Assumptions!$C$47+Assumptions!$C$57*Assumptions!$C$47*(1-Assumptions!$C$48)+Assumptions!$C$58*Assumptions!$C$47*(1-Assumptions!$C$49)+Assumptions!$C$59*Assumptions!$C$47*(1-Assumptions!$C$50))/(Assumptions!$C$56+Assumptions!$C$57+Assumptions!$C$58+Assumptions!$C$59))))+(Assumptions!$C$41*Assumptions!$C$45*((Assumptions!$C$70*Assumptions!$C$71*Assumptions!$C$63)*((Assumptions!$C$56*Assumptions!$C$47+Assumptions!$C$57*Assumptions!$C$47*(1-Assumptions!$C$48)+Assumptions!$C$58*Assumptions!$C$47*(1-Assumptions!$C$49)+Assumptions!$C$59*Assumptions!$C$47*(1-Assumptions!$C$50))/(Assumptions!$C$56+Assumptions!$C$57+Assumptions!$C$58+Assumptions!$C$59)))))*Assumptions!$C$92*Assumptions!$C$97) | D15: =Assumptions!$G$89*$B15*(D$14*((Assumptions!$C$56*Assumptions!$C$47+Assumptions!$C$57*Assumptions!$C$47*(1-Assumptions!$C$48)+Assumptions!$C$58*Assumptions!$C$47*(1-Assumptions!$C$49)+Assumptions!$C$59*Assumptions!$C$47*(1-Assumptions!$C$50))/(Assumptions!$C$56+Assumptions!$C$57+Assumptions!$C$58+Assumptions!$C$59)))*Assumptions!$C$97+(((Assumptions!$C$39*Assumptions!$C$43*((Assumptions!$C$64*Assumptions!$C$65*Assumptions!$C$63)*((Assumptions!$C$56*Assumptions!$C$47+Assumptions!$C$57*Assumptions!$C$47*(1-Assumptions!$C$48)+Assumptions!$C$58*Assumptions!$C$47*(1-Assumptions!$C$49)+Assumptions!$C$59*Assumptions!$C$47*(1-Assumptions!$C$50))/(Assumptions!$C$56+Assumptions!$C$57+Assumptions!$C$58+Assumptions!$C$59))))+(Assumptions!$C$40*Assumptions!$C$44*((Assumptions!$C$67*Assumptions!$C$68*Assumptions!$C$63)*((Assumptions!$C$56*Assumptions!$C$47+Assumptions!$C$57*Assumptions!$C$47*(1-Assumptions!$C$48)+Assumptions!$C$58*Assumptions!$C$47*(1-Assumptions!$C$49)+Assumptions!$C$59*Assumptions!$C$47*(1-Assumptions!$C$50))/(Assumptions!$C$56+Assumptions!$C$57+Assumptions!$C$58+Assumptions!$C$59))))+(Assumptions!$C$41*Assumptions!$C$45*((Assumptions!$C$70*Assumptions!$C$71*Assumptions!$C$63)*((Assumptions!$C$56*Assumptions!$C$47+Assumptions!$C$57*Assumptions!$C$47*(1-Assumptions!$C$48)+Assumptions!$C$58*Assumptions!$C$47*(1-Assumptions!$C$49)+Assumptions!$C$59*Assumptions!$C$47*(1-Assumptions!$C$50))/(Assumptions!$C$56+Assumptions!$C$57+Assumptions!$C$58+Assumptions!$C$59)))))*Assumptions!$C$92*Assumptions!$C$97) | E15: =Assumptions!$G$89*$B15*(E$14*((Assumptions!$C$56*Assumptions!$C$47+Assumptions!$C$57*Assumptions!$C$47*(1-Assumptions!$C$48)+Assumptions!$C$58*Assumptions!$C$47*(1-Assumptions!$C$49)+Assumptions!$C$59*Assumptions!$C$47*(1-Assumptions!$C$50))/(Assumptions!$C$56+Assumptions!$C$57+Assumptions!$C$58+Assumptions!$C$59)))*Assumptions!$C$97+(((Assumptions!$C$39*Assumptions!$C$43*((Assumptions!$C$64*Assumptions!$C$65*Assumptions!$C$63)*((Assumptions!$C$56*Assumptions!$C$47+Assumptions!$C$57*Assumptions!$C$47*(1-Assumptions!$C$48)+Assumptions!$C$58*Assumptions!$C$47*(1-Assumptions!$C$49)+Assumptions!$C$59*Assumptions!$C$47*(1-Assumptions!$C$50))/(Assumptions!$C$56+Assumptions!$C$57+Assumptions!$C$58+Assumptions!$C$59))))+(Assumptions!$C$40*Assumptions!$C$44*((Assumptions!$C$67*Assumptions!$C$68*Assumptions!$C$63)*((Assumptions!$C$56*Assumptions!$C$47+Assumptions!$C$57*Assumptions!$C$47*(1-Assumptions!$C$48)+Assumptions!$C$58*Assumptions!$C$47*(1-Assumptions!$C$49)+Assumptions!$C$59*Assumptions!$C$47*(1-Assumptions!$C$50))/(Assumptions!$C$56+Assumptions!$C$57+Assumptions!$C$58+Assumptions!$C$59))))+(Assumptions!$C$41*Assumptions!$C$45*((Assumptions!$C$70*Assumptions!$C$71*Assumptions!$C$63)*((Assumptions!$C$56*Assumptions!$C$47+Assumptions!$C$57*Assumptions!$C$47*(1-Assumptions!$C$48)+Assumptions!$C$58*Assumptions!$C$47*(1-Assumptions!$C$49)+Assumptions!$C$59*Assumptions!$C$47*(1-Assumptions!$C$50))/(Assumptions!$C$56+Assumptions!$C$57+Assumptions!$C$58+Assumptions!$C$59)))))*Assumptions!$C$92*Assumptions!$C$97) | F15: =Assumptions!$G$89*$B15*(F$14*((Assumptions!$C$56*Assumptions!$C$47+Assumptions!$C$57*Assumptions!$C$47*(1-Assumptions!$C$48)+Assumptions!$C$58*Assumptions!$C$47*(1-Assumptions!$C$49)+Assumptions!$C$59*Assumptions!$C$47*(1-Assumptions!$C$50))/(Assumptions!$C$56+Assumptions!$C$57+Assumptions!$C$58+Assumptions!$C$59)))*Assumptions!$C$97+(((Assumptions!$C$39*Assumptions!$C$43*((Assumptions!$C$64*Assumptions!$C$65*Assumptions!$C$63)*((Assumptions!$C$56*Assumptions!$C$47+Assumptions!$C$57*Assumptions!$C$47*(1-Assumptions!$C$48)+Assumptions!$C$58*Assumptions!$C$47*(1-Assumptions!$C$49)+Assumptions!$C$59*Assumptions!$C$47*(1-Assumptions!$C$50))/(Assumptions!$C$56+Assumptions!$C$57+Assumptions!$C$58+Assumptions!$C$59))))+(Assumptions!$C$40*Assumptions!$C$44*((Assumptions!$C$67*Assumptions!$C$68*Assumptions!$C$63)*((Assumptions!$C$56*Assumptions!$C$47+Assumptions!$C$57*Assumptions!$C$47*(1-Assumptions!$C$48)+Assumptions!$C$58*Assumptions!$C$47*(1-Assumptions!$C$49)+Assumptions!$C$59*Assumptions!$C$47*(1-Assumptions!$C$50))/(Assumptions!$C$56+Assumptions!$C$57+Assumptions!$C$58+Assumptions!$C$59))))+(Assumptions!$C$41*Assumptions!$C$45*((Assumptions!$C$70*Assumptions!$C$71*Assumptions!$C$63)*((Assumptions!$C$56*Assumptions!$C$47+Assumptions!$C$57*Assumptions!$C$47*(1-Assumptions!$C$48)+Assumptions!$C$58*Assumptions!$C$47*(1-Assumptions!$C$49)+Assumptions!$C$59*Assumptions!$C$47*(1-Assumptions!$C$50))/(Assumptions!$C$56+Assumptions!$C$57+Assumptions!$C$58+Assumptions!$C$59)))))*Assumptions!$C$92*Assumptions!$C$97) | G15: =Assumptions!$G$89*$B15*(G$14*((Assumptions!$C$56*Assumptions!$C$47+Assumptions!$C$57*Assumptions!$C$47*(1-Assumptions!$C$48)+Assumptions!$C$58*Assumptions!$C$47*(1-Assumptions!$C$49)+Assumptions!$C$59*Assumptions!$C$47*(1-Assumptions!$C$50))/(Assumptions!$C$56+Assumptions!$C$57+Assumptions!$C$58+Assumptions!$C$59)))*Assumptions!$C$97+(((Assumptions!$C$39*Assumptions!$C$43*((Assumptions!$C$64*Assumptions!$C$65*Assumptions!$C$63)*((Assumptions!$C$56*Assumptions!$C$47+Assumptions!$C$57*Assumptions!$C$47*(1-Assumptions!$C$48)+Assumptions!$C$58*Assumptions!$C$47*(1-Assumptions!$C$49)+Assumptions!$C$59*Assumptions!$C$47*(1-Assumptions!$C$50))/(Assumptions!$C$56+Assumptions!$C$57+Assumptions!$C$58+Assumptions!$C$59))))+(Assumptions!$C$40*Assumptions!$C$44*((Assumptions!$C$67*Assumptions!$C$68*Assumptions!$C$63)*((Assumptions!$C$56*Assumptions!$C$47+Assumptions!$C$57*Assumptions!$C$47*(1-Assumptions!$C$48)+Assumptions!$C$58*Assumptions!$C$47*(1-Assumptions!$C$49)+Assumptions!$C$59*Assumptions!$C$47*(1-Assumptions!$C$50))/(Assumptions!$C$56+Assumptions!$C$57+Assumptions!$C$58+Assumptions!$C$59))))+(Assumptions!$C$41*Assumptions!$C$45*((Assumptions!$C$70*Assumptions!$C$71*Assumptions!$C$63)*((Assumptions!$C$56*Assumptions!$C$47+Assumptions!$C$57*Assumptions!$C$47*(1-Assumptions!$C$48)+Assumptions!$C$58*Assumptions!$C$47*(1-Assumptions!$C$49)+Assumptions!$C$59*Assumptions!$C$47*(1-Assumptions!$C$50))/(Assumptions!$C$56+Assumptions!$C$57+Assumptions!$C$58+Assumptions!$C$59)))))*Assumptions!$C$92*Assumptions!$C$97)
B16: 0.75 | C16: =Assumptions!$G$89*$B16*(C$14*((Assumptions!$C$56*Assumptions!$C$47+Assumptions!$C$57*Assumptions!$C$47*(1-Assumptions!$C$48)+Assumptions!$C$58*Assumptions!$C$47*(1-Assumptions!$C$49)+Assumptions!$C$59*Assumptions!$C$47*(1-Assumptions!$C$50))/(Assumptions!$C$56+Assumptions!$C$57+Assumptions!$C$58+Assumptions!$C$59)))*Assumptions!$C$97+(((Assumptions!$C$39*Assumptions!$C$43*((Assumptions!$C$64*Assumptions!$C$65*Assumptions!$C$63)*((Assumptions!$C$56*Assumptions!$C$47+Assumptions!$C$57*Assumptions!$C$47*(1-Assumptions!$C$48)+Assumptions!$C$58*Assumptions!$C$47*(1-Assumptions!$C$49)+Assumptions!$C$59*Assumptions!$C$47*(1-Assumptions!$C$50))/(Assumptions!$C$56+Assumptions!$C$57+Assumptions!$C$58+Assumptions!$C$59))))+(Assumptions!$C$40*Assumptions!$C$44*((Assumptions!$C$67*Assumptions!$C$68*Assumptions!$C$63)*((Assumptions!$C$56*Assumptions!$C$47+Assumptions!$C$57*Assumptions!$C$47*(1-Assumptions!$C$48)+Assumptions!$C$58*Assumptions!$C$47*(1-Assumptions!$C$49)+Assumptions!$C$59*Assumptions!$C$47*(1-Assumptions!$C$50))/(Assumptions!$C$56+Assumptions!$C$57+Assumptions!$C$58+Assumptions!$C$59))))+(Assumptions!$C$41*Assumptions!$C$45*((Assumptions!$C$70*Assumptions!$C$71*Assumptions!$C$63)*((Assumptions!$C$56*Assumptions!$C$47+Assumptions!$C$57*Assumptions!$C$47*(1-Assumptions!$C$48)+Assumptions!$C$58*Assumptions!$C$47*(1-Assumptions!$C$49)+Assumptions!$C$59*Assumptions!$C$47*(1-Assumptions!$C$50))/(Assumptions!$C$56+Assumptions!$C$57+Assumptions!$C$58+Assumptions!$C$59)))))*Assumptions!$C$92*Assumptions!$C$97) | D16: =Assumptions!$G$89*$B16*(D$14*((Assumptions!$C$56*Assumptions!$C$47+Assumptions!$C$57*Assumptions!$C$47*(1-Assumptions!$C$48)+Assumptions!$C$58*Assumptions!$C$47*(1-Assumptions!$C$49)+Assumptions!$C$59*Assumptions!$C$47*(1-Assumptions!$C$50))/(Assumptions!$C$56+Assumptions!$C$57+Assumptions!$C$58+Assumptions!$C$59)))*Assumptions!$C$97+(((Assumptions!$C$39*Assumptions!$C$43*((Assumptions!$C$64*Assumptions!$C$65*Assumptions!$C$63)*((Assumptions!$C$56*Assumptions!$C$47+Assumptions!$C$57*Assumptions!$C$47*(1-Assumptions!$C$48)+Assumptions!$C$58*Assumptions!$C$47*(1-Assumptions!$C$49)+Assumptions!$C$59*Assumptions!$C$47*(1-Assumptions!$C$50))/(Assumptions!$C$56+Assumptions!$C$57+Assumptions!$C$58+Assumptions!$C$59))))+(Assumptions!$C$40*Assumptions!$C$44*((Assumptions!$C$67*Assumptions!$C$68*Assumptions!$C$63)*((Assumptions!$C$56*Assumptions!$C$47+Assumptions!$C$57*Assumptions!$C$47*(1-Assumptions!$C$48)+Assumptions!$C$58*Assumptions!$C$47*(1-Assumptions!$C$49)+Assumptions!$C$59*Assumptions!$C$47*(1-Assumptions!$C$50))/(Assumptions!$C$56+Assumptions!$C$57+Assumptions!$C$58+Assumptions!$C$59))))+(Assumptions!$C$41*Assumptions!$C$45*((Assumptions!$C$70*Assumptions!$C$71*Assumptions!$C$63)*((Assumptions!$C$56*Assumptions!$C$47+Assumptions!$C$57*Assumptions!$C$47*(1-Assumptions!$C$48)+Assumptions!$C$58*Assumptions!$C$47*(1-Assumptions!$C$49)+Assumptions!$C$59*Assumptions!$C$47*(1-Assumptions!$C$50))/(Assumptions!$C$56+Assumptions!$C$57+Assumptions!$C$58+Assumptions!$C$59)))))*Assumptions!$C$92*Assumptions!$C$97) | E16: =Assumptions!$G$89*$B16*(E$14*((Assumptions!$C$56*Assumptions!$C$47+Assumptions!$C$57*Assumptions!$C$47*(1-Assumptions!$C$48)+Assumptions!$C$58*Assumptions!$C$47*(1-Assumptions!$C$49)+Assumptions!$C$59*Assumptions!$C$47*(1-Assumptions!$C$50))/(Assumptions!$C$56+Assumptions!$C$57+Assumptions!$C$58+Assumptions!$C$59)))*Assumptions!$C$97+(((Assumptions!$C$39*Assumptions!$C$43*((Assumptions!$C$64*Assumptions!$C$65*Assumptions!$C$63)*((Assumptions!$C$56*Assumptions!$C$47+Assumptions!$C$57*Assumptions!$C$47*(1-Assumptions!$C$48)+Assumptions!$C$58*Assumptions!$C$47*(1-Assumptions!$C$49)+Assumptions!$C$59*Assumptions!$C$47*(1-Assumptions!$C$50))/(Assumptions!$C$56+Assumptions!$C$57+Assumptions!$C$58+Assumptions!$C$59))))+(Assumptions!$C$40*Assumptions!$C$44*((Assumptions!$C$67*Assumptions!$C$68*Assumptions!$C$63)*((Assumptions!$C$56*Assumptions!$C$47+Assumptions!$C$57*Assumptions!$C$47*(1-Assumptions!$C$48)+Assumptions!$C$58*Assumptions!$C$47*(1-Assumptions!$C$49)+Assumptions!$C$59*Assumptions!$C$47*(1-Assumptions!$C$50))/(Assumptions!$C$56+Assumptions!$C$57+Assumptions!$C$58+Assumptions!$C$59))))+(Assumptions!$C$41*Assumptions!$C$45*((Assumptions!$C$70*Assumptions!$C$71*Assumptions!$C$63)*((Assumptions!$C$56*Assumptions!$C$47+Assumptions!$C$57*Assumptions!$C$47*(1-Assumptions!$C$48)+Assumptions!$C$58*Assumptions!$C$47*(1-Assumptions!$C$49)+Assumptions!$C$59*Assumptions!$C$47*(1-Assumptions!$C$50))/(Assumptions!$C$56+Assumptions!$C$57+Assumptions!$C$58+Assumptions!$C$59)))))*Assumptions!$C$92*Assumptions!$C$97) | F16: =Assumptions!$G$89*$B16*(F$14*((Assumptions!$C$56*Assumptions!$C$47+Assumptions!$C$57*Assumptions!$C$47*(1-Assumptions!$C$48)+Assumptions!$C$58*Assumptions!$C$47*(1-Assumptions!$C$49)+Assumptions!$C$59*Assumptions!$C$47*(1-Assumptions!$C$50))/(Assumptions!$C$56+Assumptions!$C$57+Assumptions!$C$58+Assumptions!$C$59)))*Assumptions!$C$97+(((Assumptions!$C$39*Assumptions!$C$43*((Assumptions!$C$64*Assumptions!$C$65*Assumptions!$C$63)*((Assumptions!$C$56*Assumptions!$C$47+Assumptions!$C$57*Assumptions!$C$47*(1-Assumptions!$C$48)+Assumptions!$C$58*Assumptions!$C$47*(1-Assumptions!$C$49)+Assumptions!$C$59*Assumptions!$C$47*(1-Assumptions!$C$50))/(Assumptions!$C$56+Assumptions!$C$57+Assumptions!$C$58+Assumptions!$C$59))))+(Assumptions!$C$40*Assumptions!$C$44*((Assumptions!$C$67*Assumptions!$C$68*Assumptions!$C$63)*((Assumptions!$C$56*Assumptions!$C$47+Assumptions!$C$57*Assumptions!$C$47*(1-Assumptions!$C$48)+Assumptions!$C$58*Assumptions!$C$47*(1-Assumptions!$C$49)+Assumptions!$C$59*Assumptions!$C$47*(1-Assumptions!$C$50))/(Assumptions!$C$56+Assumptions!$C$57+Assumptions!$C$58+Assumptions!$C$59))))+(Assumptions!$C$41*Assumptions!$C$45*((Assumptions!$C$70*Assumptions!$C$71*Assumptions!$C$63)*((Assumptions!$C$56*Assumptions!$C$47+Assumptions!$C$57*Assumptions!$C$47*(1-Assumptions!$C$48)+Assumptions!$C$58*Assumptions!$C$47*(1-Assumptions!$C$49)+Assumptions!$C$59*Assumptions!$C$47*(1-Assumptions!$C$50))/(Assumptions!$C$56+Assumptions!$C$57+Assumptions!$C$58+Assumptions!$C$59)))))*Assumptions!$C$92*Assumptions!$C$97) | G16: =Assumptions!$G$89*$B16*(G$14*((Assumptions!$C$56*Assumptions!$C$47+Assumptions!$C$57*Assumptions!$C$47*(1-Assumptions!$C$48)+Assumptions!$C$58*Assumptions!$C$47*(1-Assumptions!$C$49)+Assumptions!$C$59*Assumptions!$C$47*(1-Assumptions!$C$50))/(Assumptions!$C$56+Assumptions!$C$57+Assumptions!$C$58+Assumptions!$C$59)))*Assumptions!$C$97+(((Assumptions!$C$39*Assumptions!$C$43*((Assumptions!$C$64*Assumptions!$C$65*Assumptions!$C$63)*((Assumptions!$C$56*Assumptions!$C$47+Assumptions!$C$57*Assumptions!$C$47*(1-Assumptions!$C$48)+Assumptions!$C$58*Assumptions!$C$47*(1-Assumptions!$C$49)+Assumptions!$C$59*Assumptions!$C$47*(1-Assumptions!$C$50))/(Assumptions!$C$56+Assumptions!$C$57+Assumptions!$C$58+Assumptions!$C$59))))+(Assumptions!$C$40*Assumptions!$C$44*((Assumptions!$C$67*Assumptions!$C$68*Assumptions!$C$63)*((Assumptions!$C$56*Assumptions!$C$47+Assumptions!$C$57*Assumptions!$C$47*(1-Assumptions!$C$48)+Assumptions!$C$58*Assumptions!$C$47*(1-Assumptions!$C$49)+Assumptions!$C$59*Assumptions!$C$47*(1-Assumptions!$C$50))/(Assumptions!$C$56+Assumptions!$C$57+Assumptions!$C$58+Assumptions!$C$59))))+(Assumptions!$C$41*Assumptions!$C$45*((Assumptions!$C$70*Assumptions!$C$71*Assumptions!$C$63)*((Assumptions!$C$56*Assumptions!$C$47+Assumptions!$C$57*Assumptions!$C$47*(1-Assumptions!$C$48)+Assumptions!$C$58*Assumptions!$C$47*(1-Assumptions!$C$49)+Assumptions!$C$59*Assumptions!$C$47*(1-Assumptions!$C$50))/(Assumptions!$C$56+Assumptions!$C$57+Assumptions!$C$58+Assumptions!$C$59)))))*Assumptions!$C$92*Assumptions!$C$97)
B17: 1 | C17: =Assumptions!$G$89*$B17*(C$14*((Assumptions!$C$56*Assumptions!$C$47+Assumptions!$C$57*Assumptions!$C$47*(1-Assumptions!$C$48)+Assumptions!$C$58*Assumptions!$C$47*(1-Assumptions!$C$49)+Assumptions!$C$59*Assumptions!$C$47*(1-Assumptions!$C$50))/(Assumptions!$C$56+Assumptions!$C$57+Assumptions!$C$58+Assumptions!$C$59)))*Assumptions!$C$97+(((Assumptions!$C$39*Assumptions!$C$43*((Assumptions!$C$64*Assumptions!$C$65*Assumptions!$C$63)*((Assumptions!$C$56*Assumptions!$C$47+Assumptions!$C$57*Assumptions!$C$47*(1-Assumptions!$C$48)+Assumptions!$C$58*Assumptions!$C$47*(1-Assumptions!$C$49)+Assumptions!$C$59*Assumptions!$C$47*(1-Assumptions!$C$50))/(Assumptions!$C$56+Assumptions!$C$57+Assumptions!$C$58+Assumptions!$C$59))))+(Assumptions!$C$40*Assumptions!$C$44*((Assumptions!$C$67*Assumptions!$C$68*Assumptions!$C$63)*((Assumptions!$C$56*Assumptions!$C$47+Assumptions!$C$57*Assumptions!$C$47*(1-Assumptions!$C$48)+Assumptions!$C$58*Assumptions!$C$47*(1-Assumptions!$C$49)+Assumptions!$C$59*Assumptions!$C$47*(1-Assumptions!$C$50))/(Assumptions!$C$56+Assumptions!$C$57+Assumptions!$C$58+Assumptions!$C$59))))+(Assumptions!$C$41*Assumptions!$C$45*((Assumptions!$C$70*Assumptions!$C$71*Assumptions!$C$63)*((Assumptions!$C$56*Assumptions!$C$47+Assumptions!$C$57*Assumptions!$C$47*(1-Assumptions!$C$48)+Assumptions!$C$58*Assumptions!$C$47*(1-Assumptions!$C$49)+Assumptions!$C$59*Assumptions!$C$47*(1-Assumptions!$C$50))/(Assumptions!$C$56+Assumptions!$C$57+Assumptions!$C$58+Assumptions!$C$59)))))*Assumptions!$C$92*Assumptions!$C$97) | D17: =Assumptions!$G$89*$B17*(D$14*((Assumptions!$C$56*Assumptions!$C$47+Assumptions!$C$57*Assumptions!$C$47*(1-Assumptions!$C$48)+Assumptions!$C$58*Assumptions!$C$47*(1-Assumptions!$C$49)+Assumptions!$C$59*Assumptions!$C$47*(1-Assumptions!$C$50))/(Assumptions!$C$56+Assumptions!$C$57+Assumptions!$C$58+Assumptions!$C$59)))*Assumptions!$C$97+(((Assumptions!$C$39*Assumptions!$C$43*((Assumptions!$C$64*Assumptions!$C$65*Assumptions!$C$63)*((Assumptions!$C$56*Assumptions!$C$47+Assumptions!$C$57*Assumptions!$C$47*(1-Assumptions!$C$48)+Assumptions!$C$58*Assumptions!$C$47*(1-Assumptions!$C$49)+Assumptions!$C$59*Assumptions!$C$47*(1-Assumptions!$C$50))/(Assumptions!$C$56+Assumptions!$C$57+Assumptions!$C$58+Assumptions!$C$59))))+(Assumptions!$C$40*Assumptions!$C$44*((Assumptions!$C$67*Assumptions!$C$68*Assumptions!$C$63)*((Assumptions!$C$56*Assumptions!$C$47+Assumptions!$C$57*Assumptions!$C$47*(1-Assumptions!$C$48)+Assumptions!$C$58*Assumptions!$C$47*(1-Assumptions!$C$49)+Assumptions!$C$59*Assumptions!$C$47*(1-Assumptions!$C$50))/(Assumptions!$C$56+Assumptions!$C$57+Assumptions!$C$58+Assumptions!$C$59))))+(Assumptions!$C$41*Assumptions!$C$45*((Assumptions!$C$70*Assumptions!$C$71*Assumptions!$C$63)*((Assumptions!$C$56*Assumptions!$C$47+Assumptions!$C$57*Assumptions!$C$47*(1-Assumptions!$C$48)+Assumptions!$C$58*Assumptions!$C$47*(1-Assumptions!$C$49)+Assumptions!$C$59*Assumptions!$C$47*(1-Assumptions!$C$50))/(Assumptions!$C$56+Assumptions!$C$57+Assumptions!$C$58+Assumptions!$C$59)))))*Assumptions!$C$92*Assumptions!$C$97) | E17: =Assumptions!$G$89*$B17*(E$14*((Assumptions!$C$56*Assumptions!$C$47+Assumptions!$C$57*Assumptions!$C$47*(1-Assumptions!$C$48)+Assumptions!$C$58*Assumptions!$C$47*(1-Assumptions!$C$49)+Assumptions!$C$59*Assumptions!$C$47*(1-Assumptions!$C$50))/(Assumptions!$C$56+Assumptions!$C$57+Assumptions!$C$58+Assumptions!$C$59)))*Assumptions!$C$97+(((Assumptions!$C$39*Assumptions!$C$43*((Assumptions!$C$64*Assumptions!$C$65*Assumptions!$C$63)*((Assumptions!$C$56*Assumptions!$C$47+Assumptions!$C$57*Assumptions!$C$47*(1-Assumptions!$C$48)+Assumptions!$C$58*Assumptions!$C$47*(1-Assumptions!$C$49)+Assumptions!$C$59*Assumptions!$C$47*(1-Assumptions!$C$50))/(Assumptions!$C$56+Assumptions!$C$57+Assumptions!$C$58+Assumptions!$C$59))))+(Assumptions!$C$40*Assumptions!$C$44*((Assumptions!$C$67*Assumptions!$C$68*Assumptions!$C$63)*((Assumptions!$C$56*Assumptions!$C$47+Assumptions!$C$57*Assumptions!$C$47*(1-Assumptions!$C$48)+Assumptions!$C$58*Assumptions!$C$47*(1-Assumptions!$C$49)+Assumptions!$C$59*Assumptions!$C$47*(1-Assumptions!$C$50))/(Assumptions!$C$56+Assumptions!$C$57+Assumptions!$C$58+Assumptions!$C$59))))+(Assumptions!$C$41*Assumptions!$C$45*((Assumptions!$C$70*Assumptions!$C$71*Assumptions!$C$63)*((Assumptions!$C$56*Assumptions!$C$47+Assumptions!$C$57*Assumptions!$C$47*(1-Assumptions!$C$48)+Assumptions!$C$58*Assumptions!$C$47*(1-Assumptions!$C$49)+Assumptions!$C$59*Assumptions!$C$47*(1-Assumptions!$C$50))/(Assumptions!$C$56+Assumptions!$C$57+Assumptions!$C$58+Assumptions!$C$59)))))*Assumptions!$C$92*Assumptions!$C$97) | F17: =Assumptions!$G$89*$B17*(F$14*((Assumptions!$C$56*Assumptions!$C$47+Assumptions!$C$57*Assumptions!$C$47*(1-Assumptions!$C$48)+Assumptions!$C$58*Assumptions!$C$47*(1-Assumptions!$C$49)+Assumptions!$C$59*Assumptions!$C$47*(1-Assumptions!$C$50))/(Assumptions!$C$56+Assumptions!$C$57+Assumptions!$C$58+Assumptions!$C$59)))*Assumptions!$C$97+(((Assumptions!$C$39*Assumptions!$C$43*((Assumptions!$C$64*Assumptions!$C$65*Assumptions!$C$63)*((Assumptions!$C$56*Assumptions!$C$47+Assumptions!$C$57*Assumptions!$C$47*(1-Assumptions!$C$48)+Assumptions!$C$58*Assumptions!$C$47*(1-Assumptions!$C$49)+Assumptions!$C$59*Assumptions!$C$47*(1-Assumptions!$C$50))/(Assumptions!$C$56+Assumptions!$C$57+Assumptions!$C$58+Assumptions!$C$59))))+(Assumptions!$C$40*Assumptions!$C$44*((Assumptions!$C$67*Assumptions!$C$68*Assumptions!$C$63)*((Assumptions!$C$56*Assumptions!$C$47+Assumptions!$C$57*Assumptions!$C$47*(1-Assumptions!$C$48)+Assumptions!$C$58*Assumptions!$C$47*(1-Assumptions!$C$49)+Assumptions!$C$59*Assumptions!$C$47*(1-Assumptions!$C$50))/(Assumptions!$C$56+Assumptions!$C$57+Assumptions!$C$58+Assumptions!$C$59))))+(Assumptions!$C$41*Assumptions!$C$45*((Assumptions!$C$70*Assumptions!$C$71*Assumptions!$C$63)*((Assumptions!$C$56*Assumptions!$C$47+Assumptions!$C$57*Assumptions!$C$47*(1-Assumptions!$C$48)+Assumptions!$C$58*Assumptions!$C$47*(1-Assumptions!$C$49)+Assumptions!$C$59*Assumptions!$C$47*(1-Assumptions!$C$50))/(Assumptions!$C$56+Assumptions!$C$57+Assumptions!$C$58+Assumptions!$C$59)))))*Assumptions!$C$92*Assumptions!$C$97) | G17: =Assumptions!$G$89*$B17*(G$14*((Assumptions!$C$56*Assumptions!$C$47+Assumptions!$C$57*Assumptions!$C$47*(1-Assumptions!$C$48)+Assumptions!$C$58*Assumptions!$C$47*(1-Assumptions!$C$49)+Assumptions!$C$59*Assumptions!$C$47*(1-Assumptions!$C$50))/(Assumptions!$C$56+Assumptions!$C$57+Assumptions!$C$58+Assumptions!$C$59)))*Assumptions!$C$97+(((Assumptions!$C$39*Assumptions!$C$43*((Assumptions!$C$64*Assumptions!$C$65*Assumptions!$C$63)*((Assumptions!$C$56*Assumptions!$C$47+Assumptions!$C$57*Assumptions!$C$47*(1-Assumptions!$C$48)+Assumptions!$C$58*Assumptions!$C$47*(1-Assumptions!$C$49)+Assumptions!$C$59*Assumptions!$C$47*(1-Assumptions!$C$50))/(Assumptions!$C$56+Assumptions!$C$57+Assumptions!$C$58+Assumptions!$C$59))))+(Assumptions!$C$40*Assumptions!$C$44*((Assumptions!$C$67*Assumptions!$C$68*Assumptions!$C$63)*((Assumptions!$C$56*Assumptions!$C$47+Assumptions!$C$57*Assumptions!$C$47*(1-Assumptions!$C$48)+Assumptions!$C$58*Assumptions!$C$47*(1-Assumptions!$C$49)+Assumptions!$C$59*Assumptions!$C$47*(1-Assumptions!$C$50))/(Assumptions!$C$56+Assumptions!$C$57+Assumptions!$C$58+Assumptions!$C$59))))+(Assumptions!$C$41*Assumptions!$C$45*((Assumptions!$C$70*Assumptions!$C$71*Assumptions!$C$63)*((Assumptions!$C$56*Assumptions!$C$47+Assumptions!$C$57*Assumptions!$C$47*(1-Assumptions!$C$48)+Assumptions!$C$58*Assumptions!$C$47*(1-Assumptions!$C$49)+Assumptions!$C$59*Assumptions!$C$47*(1-Assumptions!$C$50))/(Assumptions!$C$56+Assumptions!$C$57+Assumptions!$C$58+Assumptions!$C$59)))))*Assumptions!$C$92*Assumptions!$C$97)
B18: 1.25 | C18: =Assumptions!$G$89*$B18*(C$14*((Assumptions!$C$56*Assumptions!$C$47+Assumptions!$C$57*Assumptions!$C$47*(1-Assumptions!$C$48)+Assumptions!$C$58*Assumptions!$C$47*(1-Assumptions!$C$49)+Assumptions!$C$59*Assumptions!$C$47*(1-Assumptions!$C$50))/(Assumptions!$C$56+Assumptions!$C$57+Assumptions!$C$58+Assumptions!$C$59)))*Assumptions!$C$97+(((Assumptions!$C$39*Assumptions!$C$43*((Assumptions!$C$64*Assumptions!$C$65*Assumptions!$C$63)*((Assumptions!$C$56*Assumptions!$C$47+Assumptions!$C$57*Assumptions!$C$47*(1-Assumptions!$C$48)+Assumptions!$C$58*Assumptions!$C$47*(1-Assumptions!$C$49)+Assumptions!$C$59*Assumptions!$C$47*(1-Assumptions!$C$50))/(Assumptions!$C$56+Assumptions!$C$57+Assumptions!$C$58+Assumptions!$C$59))))+(Assumptions!$C$40*Assumptions!$C$44*((Assumptions!$C$67*Assumptions!$C$68*Assumptions!$C$63)*((Assumptions!$C$56*Assumptions!$C$47+Assumptions!$C$57*Assumptions!$C$47*(1-Assumptions!$C$48)+Assumptions!$C$58*Assumptions!$C$47*(1-Assumptions!$C$49)+Assumptions!$C$59*Assumptions!$C$47*(1-Assumptions!$C$50))/(Assumptions!$C$56+Assumptions!$C$57+Assumptions!$C$58+Assumptions!$C$59))))+(Assumptions!$C$41*Assumptions!$C$45*((Assumptions!$C$70*Assumptions!$C$71*Assumptions!$C$63)*((Assumptions!$C$56*Assumptions!$C$47+Assumptions!$C$57*Assumptions!$C$47*(1-Assumptions!$C$48)+Assumptions!$C$58*Assumptions!$C$47*(1-Assumptions!$C$49)+Assumptions!$C$59*Assumptions!$C$47*(1-Assumptions!$C$50))/(Assumptions!$C$56+Assumptions!$C$57+Assumptions!$C$58+Assumptions!$C$59)))))*Assumptions!$C$92*Assumptions!$C$97) | D18: =Assumptions!$G$89*$B18*(D$14*((Assumptions!$C$56*Assumptions!$C$47+Assumptions!$C$57*Assumptions!$C$47*(1-Assumptions!$C$48)+Assumptions!$C$58*Assumptions!$C$47*(1-Assumptions!$C$49)+Assumptions!$C$59*Assumptions!$C$47*(1-Assumptions!$C$50))/(Assumptions!$C$56+Assumptions!$C$57+Assumptions!$C$58+Assumptions!$C$59)))*Assumptions!$C$97+(((Assumptions!$C$39*Assumptions!$C$43*((Assumptions!$C$64*Assumptions!$C$65*Assumptions!$C$63)*((Assumptions!$C$56*Assumptions!$C$47+Assumptions!$C$57*Assumptions!$C$47*(1-Assumptions!$C$48)+Assumptions!$C$58*Assumptions!$C$47*(1-Assumptions!$C$49)+Assumptions!$C$59*Assumptions!$C$47*(1-Assumptions!$C$50))/(Assumptions!$C$56+Assumptions!$C$57+Assumptions!$C$58+Assumptions!$C$59))))+(Assumptions!$C$40*Assumptions!$C$44*((Assumptions!$C$67*Assumptions!$C$68*Assumptions!$C$63)*((Assumptions!$C$56*Assumptions!$C$47+Assumptions!$C$57*Assumptions!$C$47*(1-Assumptions!$C$48)+Assumptions!$C$58*Assumptions!$C$47*(1-Assumptions!$C$49)+Assumptions!$C$59*Assumptions!$C$47*(1-Assumptions!$C$50))/(Assumptions!$C$56+Assumptions!$C$57+Assumptions!$C$58+Assumptions!$C$59))))+(Assumptions!$C$41*Assumptions!$C$45*((Assumptions!$C$70*Assumptions!$C$71*Assumptions!$C$63)*((Assumptions!$C$56*Assumptions!$C$47+Assumptions!$C$57*Assumptions!$C$47*(1-Assumptions!$C$48)+Assumptions!$C$58*Assumptions!$C$47*(1-Assumptions!$C$49)+Assumptions!$C$59*Assumptions!$C$47*(1-Assumptions!$C$50))/(Assumptions!$C$56+Assumptions!$C$57+Assumptions!$C$58+Assumptions!$C$59)))))*Assumptions!$C$92*Assumptions!$C$97) | E18: =Assumptions!$G$89*$B18*(E$14*((Assumptions!$C$56*Assumptions!$C$47+Assumptions!$C$57*Assumptions!$C$47*(1-Assumptions!$C$48)+Assumptions!$C$58*Assumptions!$C$47*(1-Assumptions!$C$49)+Assumptions!$C$59*Assumptions!$C$47*(1-Assumptions!$C$50))/(Assumptions!$C$56+Assumptions!$C$57+Assumptions!$C$58+Assumptions!$C$59)))*Assumptions!$C$97+(((Assumptions!$C$39*Assumptions!$C$43*((Assumptions!$C$64*Assumptions!$C$65*Assumptions!$C$63)*((Assumptions!$C$56*Assumptions!$C$47+Assumptions!$C$57*Assumptions!$C$47*(1-Assumptions!$C$48)+Assumptions!$C$58*Assumptions!$C$47*(1-Assumptions!$C$49)+Assumptions!$C$59*Assumptions!$C$47*(1-Assumptions!$C$50))/(Assumptions!$C$56+Assumptions!$C$57+Assumptions!$C$58+Assumptions!$C$59))))+(Assumptions!$C$40*Assumptions!$C$44*((Assumptions!$C$67*Assumptions!$C$68*Assumptions!$C$63)*((Assumptions!$C$56*Assumptions!$C$47+Assumptions!$C$57*Assumptions!$C$47*(1-Assumptions!$C$48)+Assumptions!$C$58*Assumptions!$C$47*(1-Assumptions!$C$49)+Assumptions!$C$59*Assumptions!$C$47*(1-Assumptions!$C$50))/(Assumptions!$C$56+Assumptions!$C$57+Assumptions!$C$58+Assumptions!$C$59))))+(Assumptions!$C$41*Assumptions!$C$45*((Assumptions!$C$70*Assumptions!$C$71*Assumptions!$C$63)*((Assumptions!$C$56*Assumptions!$C$47+Assumptions!$C$57*Assumptions!$C$47*(1-Assumptions!$C$48)+Assumptions!$C$58*Assumptions!$C$47*(1-Assumptions!$C$49)+Assumptions!$C$59*Assumptions!$C$47*(1-Assumptions!$C$50))/(Assumptions!$C$56+Assumptions!$C$57+Assumptions!$C$58+Assumptions!$C$59)))))*Assumptions!$C$92*Assumptions!$C$97) | F18: =Assumptions!$G$89*$B18*(F$14*((Assumptions!$C$56*Assumptions!$C$47+Assumptions!$C$57*Assumptions!$C$47*(1-Assumptions!$C$48)+Assumptions!$C$58*Assumptions!$C$47*(1-Assumptions!$C$49)+Assumptions!$C$59*Assumptions!$C$47*(1-Assumptions!$C$50))/(Assumptions!$C$56+Assumptions!$C$57+Assumptions!$C$58+Assumptions!$C$59)))*Assumptions!$C$97+(((Assumptions!$C$39*Assumptions!$C$43*((Assumptions!$C$64*Assumptions!$C$65*Assumptions!$C$63)*((Assumptions!$C$56*Assumptions!$C$47+Assumptions!$C$57*Assumptions!$C$47*(1-Assumptions!$C$48)+Assumptions!$C$58*Assumptions!$C$47*(1-Assumptions!$C$49)+Assumptions!$C$59*Assumptions!$C$47*(1-Assumptions!$C$50))/(Assumptions!$C$56+Assumptions!$C$57+Assumptions!$C$58+Assumptions!$C$59))))+(Assumptions!$C$40*Assumptions!$C$44*((Assumptions!$C$67*Assumptions!$C$68*Assumptions!$C$63)*((Assumptions!$C$56*Assumptions!$C$47+Assumptions!$C$57*Assumptions!$C$47*(1-Assumptions!$C$48)+Assumptions!$C$58*Assumptions!$C$47*(1-Assumptions!$C$49)+Assumptions!$C$59*Assumptions!$C$47*(1-Assumptions!$C$50))/(Assumptions!$C$56+Assumptions!$C$57+Assumptions!$C$58+Assumptions!$C$59))))+(Assumptions!$C$41*Assumptions!$C$45*((Assumptions!$C$70*Assumptions!$C$71*Assumptions!$C$63)*((Assumptions!$C$56*Assumptions!$C$47+Assumptions!$C$57*Assumptions!$C$47*(1-Assumptions!$C$48)+Assumptions!$C$58*Assumptions!$C$47*(1-Assumptions!$C$49)+Assumptions!$C$59*Assumptions!$C$47*(1-Assumptions!$C$50))/(Assumptions!$C$56+Assumptions!$C$57+Assumptions!$C$58+Assumptions!$C$59)))))*Assumptions!$C$92*Assumptions!$C$97) | G18: =Assumptions!$G$89*$B18*(G$14*((Assumptions!$C$56*Assumptions!$C$47+Assumptions!$C$57*Assumptions!$C$47*(1-Assumptions!$C$48)+Assumptions!$C$58*Assumptions!$C$47*(1-Assumptions!$C$49)+Assumptions!$C$59*Assumptions!$C$47*(1-Assumptions!$C$50))/(Assumptions!$C$56+Assumptions!$C$57+Assumptions!$C$58+Assumptions!$C$59)))*Assumptions!$C$97+(((Assumptions!$C$39*Assumptions!$C$43*((Assumptions!$C$64*Assumptions!$C$65*Assumptions!$C$63)*((Assumptions!$C$56*Assumptions!$C$47+Assumptions!$C$57*Assumptions!$C$47*(1-Assumptions!$C$48)+Assumptions!$C$58*Assumptions!$C$47*(1-Assumptions!$C$49)+Assumptions!$C$59*Assumptions!$C$47*(1-Assumptions!$C$50))/(Assumptions!$C$56+Assumptions!$C$57+Assumptions!$C$58+Assumptions!$C$59))))+(Assumptions!$C$40*Assumptions!$C$44*((Assumptions!$C$67*Assumptions!$C$68*Assumptions!$C$63)*((Assumptions!$C$56*Assumptions!$C$47+Assumptions!$C$57*Assumptions!$C$47*(1-Assumptions!$C$48)+Assumptions!$C$58*Assumptions!$C$47*(1-Assumptions!$C$49)+Assumptions!$C$59*Assumptions!$C$47*(1-Assumptions!$C$50))/(Assumptions!$C$56+Assumptions!$C$57+Assumptions!$C$58+Assumptions!$C$59))))+(Assumptions!$C$41*Assumptions!$C$45*((Assumptions!$C$70*Assumptions!$C$71*Assumptions!$C$63)*((Assumptions!$C$56*Assumptions!$C$47+Assumptions!$C$57*Assumptions!$C$47*(1-Assumptions!$C$48)+Assumptions!$C$58*Assumptions!$C$47*(1-Assumptions!$C$49)+Assumptions!$C$59*Assumptions!$C$47*(1-Assumptions!$C$50))/(Assumptions!$C$56+Assumptions!$C$57+Assumptions!$C$58+Assumptions!$C$59)))))*Assumptions!$C$92*Assumptions!$C$97)
B19: 1.5 | C19: =Assumptions!$G$89*$B19*(C$14*((Assumptions!$C$56*Assumptions!$C$47+Assumptions!$C$57*Assumptions!$C$47*(1-Assumptions!$C$48)+Assumptions!$C$58*Assumptions!$C$47*(1-Assumptions!$C$49)+Assumptions!$C$59*Assumptions!$C$47*(1-Assumptions!$C$50))/(Assumptions!$C$56+Assumptions!$C$57+Assumptions!$C$58+Assumptions!$C$59)))*Assumptions!$C$97+(((Assumptions!$C$39*Assumptions!$C$43*((Assumptions!$C$64*Assumptions!$C$65*Assumptions!$C$63)*((Assumptions!$C$56*Assumptions!$C$47+Assumptions!$C$57*Assumptions!$C$47*(1-Assumptions!$C$48)+Assumptions!$C$58*Assumptions!$C$47*(1-Assumptions!$C$49)+Assumptions!$C$59*Assumptions!$C$47*(1-Assumptions!$C$50))/(Assumptions!$C$56+Assumptions!$C$57+Assumptions!$C$58+Assumptions!$C$59))))+(Assumptions!$C$40*Assumptions!$C$44*((Assumptions!$C$67*Assumptions!$C$68*Assumptions!$C$63)*((Assumptions!$C$56*Assumptions!$C$47+Assumptions!$C$57*Assumptions!$C$47*(1-Assumptions!$C$48)+Assumptions!$C$58*Assumptions!$C$47*(1-Assumptions!$C$49)+Assumptions!$C$59*Assumptions!$C$47*(1-Assumptions!$C$50))/(Assumptions!$C$56+Assumptions!$C$57+Assumptions!$C$58+Assumptions!$C$59))))+(Assumptions!$C$41*Assumptions!$C$45*((Assumptions!$C$70*Assumptions!$C$71*Assumptions!$C$63)*((Assumptions!$C$56*Assumptions!$C$47+Assumptions!$C$57*Assumptions!$C$47*(1-Assumptions!$C$48)+Assumptions!$C$58*Assumptions!$C$47*(1-Assumptions!$C$49)+Assumptions!$C$59*Assumptions!$C$47*(1-Assumptions!$C$50))/(Assumptions!$C$56+Assumptions!$C$57+Assumptions!$C$58+Assumptions!$C$59)))))*Assumptions!$C$92*Assumptions!$C$97) | D19: =Assumptions!$G$89*$B19*(D$14*((Assumptions!$C$56*Assumptions!$C$47+Assumptions!$C$57*Assumptions!$C$47*(1-Assumptions!$C$48)+Assumptions!$C$58*Assumptions!$C$47*(1-Assumptions!$C$49)+Assumptions!$C$59*Assumptions!$C$47*(1-Assumptions!$C$50))/(Assumptions!$C$56+Assumptions!$C$57+Assumptions!$C$58+Assumptions!$C$59)))*Assumptions!$C$97+(((Assumptions!$C$39*Assumptions!$C$43*((Assumptions!$C$64*Assumptions!$C$65*Assumptions!$C$63)*((Assumptions!$C$56*Assumptions!$C$47+Assumptions!$C$57*Assumptions!$C$47*(1-Assumptions!$C$48)+Assumptions!$C$58*Assumptions!$C$47*(1-Assumptions!$C$49)+Assumptions!$C$59*Assumptions!$C$47*(1-Assumptions!$C$50))/(Assumptions!$C$56+Assumptions!$C$57+Assumptions!$C$58+Assumptions!$C$59))))+(Assumptions!$C$40*Assumptions!$C$44*((Assumptions!$C$67*Assumptions!$C$68*Assumptions!$C$63)*((Assumptions!$C$56*Assumptions!$C$47+Assumptions!$C$57*Assumptions!$C$47*(1-Assumptions!$C$48)+Assumptions!$C$58*Assumptions!$C$47*(1-Assumptions!$C$49)+Assumptions!$C$59*Assumptions!$C$47*(1-Assumptions!$C$50))/(Assumptions!$C$56+Assumptions!$C$57+Assumptions!$C$58+Assumptions!$C$59))))+(Assumptions!$C$41*Assumptions!$C$45*((Assumptions!$C$70*Assumptions!$C$71*Assumptions!$C$63)*((Assumptions!$C$56*Assumptions!$C$47+Assumptions!$C$57*Assumptions!$C$47*(1-Assumptions!$C$48)+Assumptions!$C$58*Assumptions!$C$47*(1-Assumptions!$C$49)+Assumptions!$C$59*Assumptions!$C$47*(1-Assumptions!$C$50))/(Assumptions!$C$56+Assumptions!$C$57+Assumptions!$C$58+Assumptions!$C$59)))))*Assumptions!$C$92*Assumptions!$C$97) | E19: =Assumptions!$G$89*$B19*(E$14*((Assumptions!$C$56*Assumptions!$C$47+Assumptions!$C$57*Assumptions!$C$47*(1-Assumptions!$C$48)+Assumptions!$C$58*Assumptions!$C$47*(1-Assumptions!$C$49)+Assumptions!$C$59*Assumptions!$C$47*(1-Assumptions!$C$50))/(Assumptions!$C$56+Assumptions!$C$57+Assumptions!$C$58+Assumptions!$C$59)))*Assumptions!$C$97+(((Assumptions!$C$39*Assumptions!$C$43*((Assumptions!$C$64*Assumptions!$C$65*Assumptions!$C$63)*((Assumptions!$C$56*Assumptions!$C$47+Assumptions!$C$57*Assumptions!$C$47*(1-Assumptions!$C$48)+Assumptions!$C$58*Assumptions!$C$47*(1-Assumptions!$C$49)+Assumptions!$C$59*Assumptions!$C$47*(1-Assumptions!$C$50))/(Assumptions!$C$56+Assumptions!$C$57+Assumptions!$C$58+Assumptions!$C$59))))+(Assumptions!$C$40*Assumptions!$C$44*((Assumptions!$C$67*Assumptions!$C$68*Assumptions!$C$63)*((Assumptions!$C$56*Assumptions!$C$47+Assumptions!$C$57*Assumptions!$C$47*(1-Assumptions!$C$48)+Assumptions!$C$58*Assumptions!$C$47*(1-Assumptions!$C$49)+Assumptions!$C$59*Assumptions!$C$47*(1-Assumptions!$C$50))/(Assumptions!$C$56+Assumptions!$C$57+Assumptions!$C$58+Assumptions!$C$59))))+(Assumptions!$C$41*Assumptions!$C$45*((Assumptions!$C$70*Assumptions!$C$71*Assumptions!$C$63)*((Assumptions!$C$56*Assumptions!$C$47+Assumptions!$C$57*Assumptions!$C$47*(1-Assumptions!$C$48)+Assumptions!$C$58*Assumptions!$C$47*(1-Assumptions!$C$49)+Assumptions!$C$59*Assumptions!$C$47*(1-Assumptions!$C$50))/(Assumptions!$C$56+Assumptions!$C$57+Assumptions!$C$58+Assumptions!$C$59)))))*Assumptions!$C$92*Assumptions!$C$97) | F19: =Assumptions!$G$89*$B19*(F$14*((Assumptions!$C$56*Assumptions!$C$47+Assumptions!$C$57*Assumptions!$C$47*(1-Assumptions!$C$48)+Assumptions!$C$58*Assumptions!$C$47*(1-Assumptions!$C$49)+Assumptions!$C$59*Assumptions!$C$47*(1-Assumptions!$C$50))/(Assumptions!$C$56+Assumptions!$C$57+Assumptions!$C$58+Assumptions!$C$59)))*Assumptions!$C$97+(((Assumptions!$C$39*Assumptions!$C$43*((Assumptions!$C$64*Assumptions!$C$65*Assumptions!$C$63)*((Assumptions!$C$56*Assumptions!$C$47+Assumptions!$C$57*Assumptions!$C$47*(1-Assumptions!$C$48)+Assumptions!$C$58*Assumptions!$C$47*(1-Assumptions!$C$49)+Assumptions!$C$59*Assumptions!$C$47*(1-Assumptions!$C$50))/(Assumptions!$C$56+Assumptions!$C$57+Assumptions!$C$58+Assumptions!$C$59))))+(Assumptions!$C$40*Assumptions!$C$44*((Assumptions!$C$67*Assumptions!$C$68*Assumptions!$C$63)*((Assumptions!$C$56*Assumptions!$C$47+Assumptions!$C$57*Assumptions!$C$47*(1-Assumptions!$C$48)+Assumptions!$C$58*Assumptions!$C$47*(1-Assumptions!$C$49)+Assumptions!$C$59*Assumptions!$C$47*(1-Assumptions!$C$50))/(Assumptions!$C$56+Assumptions!$C$57+Assumptions!$C$58+Assumptions!$C$59))))+(Assumptions!$C$41*Assumptions!$C$45*((Assumptions!$C$70*Assumptions!$C$71*Assumptions!$C$63)*((Assumptions!$C$56*Assumptions!$C$47+Assumptions!$C$57*Assumptions!$C$47*(1-Assumptions!$C$48)+Assumptions!$C$58*Assumptions!$C$47*(1-Assumptions!$C$49)+Assumptions!$C$59*Assumptions!$C$47*(1-Assumptions!$C$50))/(Assumptions!$C$56+Assumptions!$C$57+Assumptions!$C$58+Assumptions!$C$59)))))*Assumptions!$C$92*Assumptions!$C$97) | G19: =Assumptions!$G$89*$B19*(G$14*((Assumptions!$C$56*Assumptions!$C$47+Assumptions!$C$57*Assumptions!$C$47*(1-Assumptions!$C$48)+Assumptions!$C$58*Assumptions!$C$47*(1-Assumptions!$C$49)+Assumptions!$C$59*Assumptions!$C$47*(1-Assumptions!$C$50))/(Assumptions!$C$56+Assumptions!$C$57+Assumptions!$C$58+Assumptions!$C$59)))*Assumptions!$C$97+(((Assumptions!$C$39*Assumptions!$C$43*((Assumptions!$C$64*Assumptions!$C$65*Assumptions!$C$63)*((Assumptions!$C$56*Assumptions!$C$47+Assumptions!$C$57*Assumptions!$C$47*(1-Assumptions!$C$48)+Assumptions!$C$58*Assumptions!$C$47*(1-Assumptions!$C$49)+Assumptions!$C$59*Assumptions!$C$47*(1-Assumptions!$C$50))/(Assumptions!$C$56+Assumptions!$C$57+Assumptions!$C$58+Assumptions!$C$59))))+(Assumptions!$C$40*Assumptions!$C$44*((Assumptions!$C$67*Assumptions!$C$68*Assumptions!$C$63)*((Assumptions!$C$56*Assumptions!$C$47+Assumptions!$C$57*Assumptions!$C$47*(1-Assumptions!$C$48)+Assumptions!$C$58*Assumptions!$C$47*(1-Assumptions!$C$49)+Assumptions!$C$59*Assumptions!$C$47*(1-Assumptions!$C$50))/(Assumptions!$C$56+Assumptions!$C$57+Assumptions!$C$58+Assumptions!$C$59))))+(Assumptions!$C$41*Assumptions!$C$45*((Assumptions!$C$70*Assumptions!$C$71*Assumptions!$C$63)*((Assumptions!$C$56*Assumptions!$C$47+Assumptions!$C$57*Assumptions!$C$47*(1-Assumptions!$C$48)+Assumptions!$C$58*Assumptions!$C$47*(1-Assumptions!$C$49)+Assumptions!$C$59*Assumptions!$C$47*(1-Assumptions!$C$50))/(Assumptions!$C$56+Assumptions!$C$57+Assumptions!$C$58+Assumptions!$C$59)))))*Assumptions!$C$92*Assumptions!$C$97)
B22: Tornado: SOM swing from +/- moves in each driver
B23: Driver | C23: Low case | D23: Base | E23: High case
B24: Channel attach scalar (0.5 / 1.0 / 1.5) | C24: =Assumptions!$G$89*0.5*(Assumptions!$C$75*((Assumptions!$C$56*Assumptions!$C$47+Assumptions!$C$57*Assumptions!$C$47*(1-Assumptions!$C$48)+Assumptions!$C$58*Assumptions!$C$47*(1-Assumptions!$C$49)+Assumptions!$C$59*Assumptions!$C$47*(1-Assumptions!$C$50))/(Assumptions!$C$56+Assumptions!$C$57+Assumptions!$C$58+Assumptions!$C$59)))*Assumptions!$C$97+(((Assumptions!$C$39*Assumptions!$C$43*((Assumptions!$C$64*Assumptions!$C$65*Assumptions!$C$63)*((Assumptions!$C$56*Assumptions!$C$47+Assumptions!$C$57*Assumptions!$C$47*(1-Assumptions!$C$48)+Assumptions!$C$58*Assumptions!$C$47*(1-Assumptions!$C$49)+Assumptions!$C$59*Assumptions!$C$47*(1-Assumptions!$C$50))/(Assumptions!$C$56+Assumptions!$C$57+Assumptions!$C$58+Assumptions!$C$59))))+(Assumptions!$C$40*Assumptions!$C$44*((Assumptions!$C$67*Assumptions!$C$68*Assumptions!$C$63)*((Assumptions!$C$56*Assumptions!$C$47+Assumptions!$C$57*Assumptions!$C$47*(1-Assumptions!$C$48)+Assumptions!$C$58*Assumptions!$C$47*(1-Assumptions!$C$49)+Assumptions!$C$59*Assumptions!$C$47*(1-Assumptions!$C$50))/(Assumptions!$C$56+Assumptions!$C$57+Assumptions!$C$58+Assumptions!$C$59))))+(Assumptions!$C$41*Assumptions!$C$45*((Assumptions!$C$70*Assumptions!$C$71*Assumptions!$C$63)*((Assumptions!$C$56*Assumptions!$C$47+Assumptions!$C$57*Assumptions!$C$47*(1-Assumptions!$C$48)+Assumptions!$C$58*Assumptions!$C$47*(1-Assumptions!$C$49)+Assumptions!$C$59*Assumptions!$C$47*(1-Assumptions!$C$50))/(Assumptions!$C$56+Assumptions!$C$57+Assumptions!$C$58+Assumptions!$C$59)))))*Assumptions!$C$92*Assumptions!$C$97) | D24: =Assumptions!$G$89*Assumptions!$C$90*(Assumptions!$C$75*((Assumptions!$C$56*Assumptions!$C$47+Assumptions!$C$57*Assumptions!$C$47*(1-Assumptions!$C$48)+Assumptions!$C$58*Assumptions!$C$47*(1-Assumptions!$C$49)+Assumptions!$C$59*Assumptions!$C$47*(1-Assumptions!$C$50))/(Assumptions!$C$56+Assumptions!$C$57+Assumptions!$C$58+Assumptions!$C$59)))*Assumptions!$C$97+(((Assumptions!$C$39*Assumptions!$C$43*((Assumptions!$C$64*Assumptions!$C$65*Assumptions!$C$63)*((Assumptions!$C$56*Assumptions!$C$47+Assumptions!$C$57*Assumptions!$C$47*(1-Assumptions!$C$48)+Assumptions!$C$58*Assumptions!$C$47*(1-Assumptions!$C$49)+Assumptions!$C$59*Assumptions!$C$47*(1-Assumptions!$C$50))/(Assumptions!$C$56+Assumptions!$C$57+Assumptions!$C$58+Assumptions!$C$59))))+(Assumptions!$C$40*Assumptions!$C$44*((Assumptions!$C$67*Assumptions!$C$68*Assumptions!$C$63)*((Assumptions!$C$56*Assumptions!$C$47+Assumptions!$C$57*Assumptions!$C$47*(1-Assumptions!$C$48)+Assumptions!$C$58*Assumptions!$C$47*(1-Assumptions!$C$49)+Assumptions!$C$59*Assumptions!$C$47*(1-Assumptions!$C$50))/(Assumptions!$C$56+Assumptions!$C$57+Assumptions!$C$58+Assumptions!$C$59))))+(Assumptions!$C$41*Assumptions!$C$45*((Assumptions!$C$70*Assumptions!$C$71*Assumptions!$C$63)*((Assumptions!$C$56*Assumptions!$C$47+Assumptions!$C$57*Assumptions!$C$47*(1-Assumptions!$C$48)+Assumptions!$C$58*Assumptions!$C$47*(1-Assumptions!$C$49)+Assumptions!$C$59*Assumptions!$C$47*(1-Assumptions!$C$50))/(Assumptions!$C$56+Assumptions!$C$57+Assumptions!$C$58+Assumptions!$C$59)))))*Assumptions!$C$92*Assumptions!$C$97) | E24: =Assumptions!$G$89*1.5*(Assumptions!$C$75*((Assumptions!$C$56*Assumptions!$C$47+Assumptions!$C$57*Assumptions!$C$47*(1-Assumptions!$C$48)+Assumptions!$C$58*Assumptions!$C$47*(1-Assumptions!$C$49)+Assumptions!$C$59*Assumptions!$C$47*(1-Assumptions!$C$50))/(Assumptions!$C$56+Assumptions!$C$57+Assumptions!$C$58+Assumptions!$C$59)))*Assumptions!$C$97+(((Assumptions!$C$39*Assumptions!$C$43*((Assumptions!$C$64*Assumptions!$C$65*Assumptions!$C$63)*((Assumptions!$C$56*Assumptions!$C$47+Assumptions!$C$57*Assumptions!$C$47*(1-Assumptions!$C$48)+Assumptions!$C$58*Assumptions!$C$47*(1-Assumptions!$C$49)+Assumptions!$C$59*Assumptions!$C$47*(1-Assumptions!$C$50))/(Assumptions!$C$56+Assumptions!$C$57+Assumptions!$C$58+Assumptions!$C$59))))+(Assumptions!$C$40*Assumptions!$C$44*((Assumptions!$C$67*Assumptions!$C$68*Assumptions!$C$63)*((Assumptions!$C$56*Assumptions!$C$47+Assumptions!$C$57*Assumptions!$C$47*(1-Assumptions!$C$48)+Assumptions!$C$58*Assumptions!$C$47*(1-Assumptions!$C$49)+Assumptions!$C$59*Assumptions!$C$47*(1-Assumptions!$C$50))/(Assumptions!$C$56+Assumptions!$C$57+Assumptions!$C$58+Assumptions!$C$59))))+(Assumptions!$C$41*Assumptions!$C$45*((Assumptions!$C$70*Assumptions!$C$71*Assumptions!$C$63)*((Assumptions!$C$56*Assumptions!$C$47+Assumptions!$C$57*Assumptions!$C$47*(1-Assumptions!$C$48)+Assumptions!$C$58*Assumptions!$C$47*(1-Assumptions!$C$49)+Assumptions!$C$59*Assumptions!$C$47*(1-Assumptions!$C$50))/(Assumptions!$C$56+Assumptions!$C$57+Assumptions!$C$58+Assumptions!$C$59)))))*Assumptions!$C$92*Assumptions!$C$97)
B25: Channel tests/account (100 / base / 300) | C25: =Assumptions!$G$89*Assumptions!$C$90*(100*((Assumptions!$C$56*Assumptions!$C$47+Assumptions!$C$57*Assumptions!$C$47*(1-Assumptions!$C$48)+Assumptions!$C$58*Assumptions!$C$47*(1-Assumptions!$C$49)+Assumptions!$C$59*Assumptions!$C$47*(1-Assumptions!$C$50))/(Assumptions!$C$56+Assumptions!$C$57+Assumptions!$C$58+Assumptions!$C$59)))*Assumptions!$C$97+(((Assumptions!$C$39*Assumptions!$C$43*((Assumptions!$C$64*Assumptions!$C$65*Assumptions!$C$63)*((Assumptions!$C$56*Assumptions!$C$47+Assumptions!$C$57*Assumptions!$C$47*(1-Assumptions!$C$48)+Assumptions!$C$58*Assumptions!$C$47*(1-Assumptions!$C$49)+Assumptions!$C$59*Assumptions!$C$47*(1-Assumptions!$C$50))/(Assumptions!$C$56+Assumptions!$C$57+Assumptions!$C$58+Assumptions!$C$59))))+(Assumptions!$C$40*Assumptions!$C$44*((Assumptions!$C$67*Assumptions!$C$68*Assumptions!$C$63)*((Assumptions!$C$56*Assumptions!$C$47+Assumptions!$C$57*Assumptions!$C$47*(1-Assumptions!$C$48)+Assumptions!$C$58*Assumptions!$C$47*(1-Assumptions!$C$49)+Assumptions!$C$59*Assumptions!$C$47*(1-Assumptions!$C$50))/(Assumptions!$C$56+Assumptions!$C$57+Assumptions!$C$58+Assumptions!$C$59))))+(Assumptions!$C$41*Assumptions!$C$45*((Assumptions!$C$70*Assumptions!$C$71*Assumptions!$C$63)*((Assumptions!$C$56*Assumptions!$C$47+Assumptions!$C$57*Assumptions!$C$47*(1-Assumptions!$C$48)+Assumptions!$C$58*Assumptions!$C$47*(1-Assumptions!$C$49)+Assumptions!$C$59*Assumptions!$C$47*(1-Assumptions!$C$50))/(Assumptions!$C$56+Assumptions!$C$57+Assumptions!$C$58+Assumptions!$C$59)))))*Assumptions!$C$92*Assumptions!$C$97) | D25: =Assumptions!$G$89*Assumptions!$C$90*(Assumptions!$C$75*((Assumptions!$C$56*Assumptions!$C$47+Assumptions!$C$57*Assumptions!$C$47*(1-Assumptions!$C$48)+Assumptions!$C$58*Assumptions!$C$47*(1-Assumptions!$C$49)+Assumptions!$C$59*Assumptions!$C$47*(1-Assumptions!$C$50))/(Assumptions!$C$56+Assumptions!$C$57+Assumptions!$C$58+Assumptions!$C$59)))*Assumptions!$C$97+(((Assumptions!$C$39*Assumptions!$C$43*((Assumptions!$C$64*Assumptions!$C$65*Assumptions!$C$63)*((Assumptions!$C$56*Assumptions!$C$47+Assumptions!$C$57*Assumptions!$C$47*(1-Assumptions!$C$48)+Assumptions!$C$58*Assumptions!$C$47*(1-Assumptions!$C$49)+Assumptions!$C$59*Assumptions!$C$47*(1-Assumptions!$C$50))/(Assumptions!$C$56+Assumptions!$C$57+Assumptions!$C$58+Assumptions!$C$59))))+(Assumptions!$C$40*Assumptions!$C$44*((Assumptions!$C$67*Assumptions!$C$68*Assumptions!$C$63)*((Assumptions!$C$56*Assumptions!$C$47+Assumptions!$C$57*Assumptions!$C$47*(1-Assumptions!$C$48)+Assumptions!$C$58*Assumptions!$C$47*(1-Assumptions!$C$49)+Assumptions!$C$59*Assumptions!$C$47*(1-Assumptions!$C$50))/(Assumptions!$C$56+Assumptions!$C$57+Assumptions!$C$58+Assumptions!$C$59))))+(Assumptions!$C$41*Assumptions!$C$45*((Assumptions!$C$70*Assumptions!$C$71*Assumptions!$C$63)*((Assumptions!$C$56*Assumptions!$C$47+Assumptions!$C$57*Assumptions!$C$47*(1-Assumptions!$C$48)+Assumptions!$C$58*Assumptions!$C$47*(1-Assumptions!$C$49)+Assumptions!$C$59*Assumptions!$C$47*(1-Assumptions!$C$50))/(Assumptions!$C$56+Assumptions!$C$57+Assumptions!$C$58+Assumptions!$C$59)))))*Assumptions!$C$92*Assumptions!$C$97) | E25: =Assumptions!$G$89*Assumptions!$C$90*(300*((Assumptions!$C$56*Assumptions!$C$47+Assumptions!$C$57*Assumptions!$C$47*(1-Assumptions!$C$48)+Assumptions!$C$58*Assumptions!$C$47*(1-Assumptions!$C$49)+Assumptions!$C$59*Assumptions!$C$47*(1-Assumptions!$C$50))/(Assumptions!$C$56+Assumptions!$C$57+Assumptions!$C$58+Assumptions!$C$59)))*Assumptions!$C$97+(((Assumptions!$C$39*Assumptions!$C$43*((Assumptions!$C$64*Assumptions!$C$65*Assumptions!$C$63)*((Assumptions!$C$56*Assumptions!$C$47+Assumptions!$C$57*Assumptions!$C$47*(1-Assumptions!$C$48)+Assumptions!$C$58*Assumptions!$C$47*(1-Assumptions!$C$49)+Assumptions!$C$59*Assumptions!$C$47*(1-Assumptions!$C$50))/(Assumptions!$C$56+Assumptions!$C$57+Assumptions!$C$58+Assumptions!$C$59))))+(Assumptions!$C$40*Assumptions!$C$44*((Assumptions!$C$67*Assumptions!$C$68*Assumptions!$C$63)*((Assumptions!$C$56*Assumptions!$C$47+Assumptions!$C$57*Assumptions!$C$47*(1-Assumptions!$C$48)+Assumptions!$C$58*Assumptions!$C$47*(1-Assumptions!$C$49)+Assumptions!$C$59*Assumptions!$C$47*(1-Assumptions!$C$50))/(Assumptions!$C$56+Assumptions!$C$57+Assumptions!$C$58+Assumptions!$C$59))))+(Assumptions!$C$41*Assumptions!$C$45*((Assumptions!$C$70*Assumptions!$C$71*Assumptions!$C$63)*((Assumptions!$C$56*Assumptions!$C$47+Assumptions!$C$57*Assumptions!$C$47*(1-Assumptions!$C$48)+Assumptions!$C$58*Assumptions!$C$47*(1-Assumptions!$C$49)+Assumptions!$C$59*Assumptions!$C$47*(1-Assumptions!$C$50))/(Assumptions!$C$56+Assumptions!$C$57+Assumptions!$C$58+Assumptions!$C$59)))))*Assumptions!$C$92*Assumptions!$C$97)
B26: PAYG price/test ($10 / base $14 / $20) | C26: =Assumptions!$G$89*Assumptions!$C$90*(Assumptions!$C$75*((Assumptions!$C$56*10+Assumptions!$C$57*10*(1-Assumptions!$C$48)+Assumptions!$C$58*10*(1-Assumptions!$C$49)+Assumptions!$C$59*10*(1-Assumptions!$C$50))/(Assumptions!$C$56+Assumptions!$C$57+Assumptions!$C$58+Assumptions!$C$59)))*Assumptions!$C$97+(((Assumptions!$C$39*Assumptions!$C$43*((Assumptions!$C$64*Assumptions!$C$65*Assumptions!$C$63)*((Assumptions!$C$56*10+Assumptions!$C$57*10*(1-Assumptions!$C$48)+Assumptions!$C$58*10*(1-Assumptions!$C$49)+Assumptions!$C$59*10*(1-Assumptions!$C$50))/(Assumptions!$C$56+Assumptions!$C$57+Assumptions!$C$58+Assumptions!$C$59))))+(Assumptions!$C$40*Assumptions!$C$44*((Assumptions!$C$67*Assumptions!$C$68*Assumptions!$C$63)*((Assumptions!$C$56*10+Assumptions!$C$57*10*(1-Assumptions!$C$48)+Assumptions!$C$58*10*(1-Assumptions!$C$49)+Assumptions!$C$59*10*(1-Assumptions!$C$50))/(Assumptions!$C$56+Assumptions!$C$57+Assumptions!$C$58+Assumptions!$C$59))))+(Assumptions!$C$41*Assumptions!$C$45*((Assumptions!$C$70*Assumptions!$C$71*Assumptions!$C$63)*((Assumptions!$C$56*10+Assumptions!$C$57*10*(1-Assumptions!$C$48)+Assumptions!$C$58*10*(1-Assumptions!$C$49)+Assumptions!$C$59*10*(1-Assumptions!$C$50))/(Assumptions!$C$56+Assumptions!$C$57+Assumptions!$C$58+Assumptions!$C$59)))))*Assumptions!$C$92*Assumptions!$C$97) | D26: =Assumptions!$G$89*Assumptions!$C$90*(Assumptions!$C$75*((Assumptions!$C$56*Assumptions!$C$47+Assumptions!$C$57*Assumptions!$C$47*(1-Assumptions!$C$48)+Assumptions!$C$58*Assumptions!$C$47*(1-Assumptions!$C$49)+Assumptions!$C$59*Assumptions!$C$47*(1-Assumptions!$C$50))/(Assumptions!$C$56+Assumptions!$C$57+Assumptions!$C$58+Assumptions!$C$59)))*Assumptions!$C$97+(((Assumptions!$C$39*Assumptions!$C$43*((Assumptions!$C$64*Assumptions!$C$65*Assumptions!$C$63)*((Assumptions!$C$56*Assumptions!$C$47+Assumptions!$C$57*Assumptions!$C$47*(1-Assumptions!$C$48)+Assumptions!$C$58*Assumptions!$C$47*(1-Assumptions!$C$49)+Assumptions!$C$59*Assumptions!$C$47*(1-Assumptions!$C$50))/(Assumptions!$C$56+Assumptions!$C$57+Assumptions!$C$58+Assumptions!$C$59))))+(Assumptions!$C$40*Assumptions!$C$44*((Assumptions!$C$67*Assumptions!$C$68*Assumptions!$C$63)*((Assumptions!$C$56*Assumptions!$C$47+Assumptions!$C$57*Assumptions!$C$47*(1-Assumptions!$C$48)+Assumptions!$C$58*Assumptions!$C$47*(1-Assumptions!$C$49)+Assumptions!$C$59*Assumptions!$C$47*(1-Assumptions!$C$50))/(Assumptions!$C$56+Assumptions!$C$57+Assumptions!$C$58+Assumptions!$C$59))))+(Assumptions!$C$41*Assumptions!$C$45*((Assumptions!$C$70*Assumptions!$C$71*Assumptions!$C$63)*((Assumptions!$C$56*Assumptions!$C$47+Assumptions!$C$57*Assumptions!$C$47*(1-Assumptions!$C$48)+Assumptions!$C$58*Assumptions!$C$47*(1-Assumptions!$C$49)+Assumptions!$C$59*Assumptions!$C$47*(1-Assumptions!$C$50))/(Assumptions!$C$56+Assumptions!$C$57+Assumptions!$C$58+Assumptions!$C$59)))))*Assumptions!$C$92*Assumptions!$C$97) | E26: =Assumptions!$G$89*Assumptions!$C$90*(Assumptions!$C$75*((Assumptions!$C$56*20+Assumptions!$C$57*20*(1-Assumptions!$C$48)+Assumptions!$C$58*20*(1-Assumptions!$C$49)+Assumptions!$C$59*20*(1-Assumptions!$C$50))/(Assumptions!$C$56+Assumptions!$C$57+Assumptions!$C$58+Assumptions!$C$59)))*Assumptions!$C$97+(((Assumptions!$C$39*Assumptions!$C$43*((Assumptions!$C$64*Assumptions!$C$65*Assumptions!$C$63)*((Assumptions!$C$56*20+Assumptions!$C$57*20*(1-Assumptions!$C$48)+Assumptions!$C$58*20*(1-Assumptions!$C$49)+Assumptions!$C$59*20*(1-Assumptions!$C$50))/(Assumptions!$C$56+Assumptions!$C$57+Assumptions!$C$58+Assumptions!$C$59))))+(Assumptions!$C$40*Assumptions!$C$44*((Assumptions!$C$67*Assumptions!$C$68*Assumptions!$C$63)*((Assumptions!$C$56*20+Assumptions!$C$57*20*(1-Assumptions!$C$48)+Assumptions!$C$58*20*(1-Assumptions!$C$49)+Assumptions!$C$59*20*(1-Assumptions!$C$50))/(Assumptions!$C$56+Assumptions!$C$57+Assumptions!$C$58+Assumptions!$C$59))))+(Assumptions!$C$41*Assumptions!$C$45*((Assumptions!$C$70*Assumptions!$C$71*Assumptions!$C$63)*((Assumptions!$C$56*20+Assumptions!$C$57*20*(1-Assumptions!$C$48)+Assumptions!$C$58*20*(1-Assumptions!$C$49)+Assumptions!$C$59*20*(1-Assumptions!$C$50))/(Assumptions!$C$56+Assumptions!$C$57+Assumptions!$C$58+Assumptions!$C$59)))))*Assumptions!$C$92*Assumptions!$C$97)

Sheet Sources
B2: INVIRTUS - Sources
B3: One row per researched input. Figures triangulated where official counts are absent; confidence noted.
B5: Key | C5: Input | D5: Source | E5: URL | F5: Date | G5: Conf.
B6: S1 | C6: France: agencies & firm counts | D6: INSEE SIRENE (7810Z/7820Z); Modeles de Business Plan | E6: public.opendatasoft.com/explore/dataset/economicref-france-sirene-v3 ; modelesdebusinessplan.com/blogs/infos/nombre-cabinets-recrutement-france | F6: 2026-06-16 | G6: High/Low
B7: S2 | C7: UK: agencies & firm counts | D7: REC / ONS / Dealroom (triangulated) | E7: rec.uk.com ; ons.gov.uk | F7: 2026-06-16 | G7: Med
B8: S3 | C8: UAE: tech firms & mid-size | D8: DIC; MAGNiTT; DIFC 2024; UAE Min. of Economy (557k SMEs) | E8: magnitt.com/en-ae/startups ; thenationalnews.com/business/economy/2023/04/06 | F8: 2026-06-16 | G8: Med
B9: S4 | C9: Morocco: agencies, tech & mid-size | D9: EcoActu/MIEPEEC; OMTPME 2025; UM6P; APEBI | E9: ecoactu.ma/lintermediation-emploi ; lematin.ma (OMTPME 2025) | F9: 2026-06-16 | G9: Med/Low
B10: S5 | C10: KSA: tech firms & mid-size | D10: Monsha'at SME Monitor Q4'23 (18,723 medium); CST Manassa (1,000+) | E10: argaam.com/en/article/articledetail/id/1709526 ; my.gov.sa/en/news/10102 | F10: 2026-06-16 | G10: Med/High
B11: S6 | C11: Egypt: tech firms & mid-size | D11: CAPMAS 5th Economic Census; ITIDA Outlook 2026; MAGNiTT | E11: censusinfo.capmas.gov.eg ; itida.gov.eg ; magnitt.com/en-eg/startups | F11: 2026-06-16 | G11: Med/Low
B12: S7 | C12: Pricing: $14/test + packs (finalized BP); benchmarked | D12: Invirtus finalized BP (Aida); TestGorilla; TestDome; Adaface; HackerRank pricing | E12: Invirtus_business_plan.xlsx ; testgorilla.com/pricing ; testdome.com/pricing ; adaface.com/pricing | F12: 2026-06-17 | G12: High
B13: S8 | C13: Traction: Manatal, retention, value anchor, funnel | D13: Invirtus April 2026 IC Update; GTM notes (34V Notion) | E13: Notion: Invirtus - April 2026 IC Update ; Invirtus - GTM | F13: 2026-06-16 | G13: Co. data
B14: S9 | C14: Second ATS (Socium) - upside | D14: Invirtus GTM notes (integration being explored) | E14: Notion: Invirtus - GTM | F14: 2026-06-16 | G14: Co. data
B16: Methodology note: 'medium enterprise' bands differ by country (KSA 50-249 emp; Morocco turnover-based 50-175M MAD; UAE <200 emp; Egypt 50+ emp census band). Mid-size counts are the closest official proxy x an engineer-hiring share. The engineer-hiring share and use-case-fit % are the softest inputs - pressure-test before locking TAM.
